<declaration>
		<dateDepot>11/07/2024 17:38:26</dateDepot>
		<uuid>f919b5d3-63e9-46aa-9746-1a3fe07f0ce5</uuid>
		<origine>ADEL</origine>
		<complete>true</complete>
		<attachedFiles>
			<attachedFiles>
				<fileName>VUE_PDF_DU_RECEPISSE_DU_DEPOT_XML</fileName>
				<serverFileName/>
				<base64EncodedContent/>
			</attachedFiles>
		</attachedFiles>
		<declarationVersion>20171221</declarationVersion>
		<activConsultantDto>
			<items/>
			<neant>true</neant>
		</activConsultantDto>
		<activProfCinqDerniereDto>
			<items>
				<items>
					<motif>
						<id>CREATION</id>
						<label/>
					</motif>
					<commentaire/>
					<conservee>true</conservee>
					<description>Vente de vins</description>
					<employeur>VINS HENRI MAIRE</employeur>
					<remuneration>
						<brutNet>Net</brutNet>
						<montant>
							<montant>
								<annee>2020</annee>
								<montant>174</montant>
							</montant>
						</montant>
					</remuneration>
					<dateDebut>01/2020</dateDebut>
					<dateFin>12/2020</dateFin>
				</items>
				<items>
					<motif>
						<id>CREATION</id>
						<label/>
					</motif>
					<commentaire/>
					<description>Repr&#xe9;sentant de commerce</description>
					<employeur>Henri MAIRE</employeur>
					<remuneration>
						<brutNet>Net</brutNet>
						<montant>
							<montant>
								<annee>2021</annee>
								<montant>228</montant>
							</montant>
						</montant>
					</remuneration>
					<dateDebut>01/2021</dateDebut>
					<dateFin>12/2021</dateFin>
				</items>
				<items>
					<motif>
						<id>CREATION</id>
						<label/>
					</motif>
					<commentaire/>
					<conservee>true</conservee>
					<description>Vente de vins</description>
					<employeur>Henri maire</employeur>
					<remuneration>
						<brutNet>Net</brutNet>
						<montant>
							<montant>
								<annee>2023</annee>
								<montant>199</montant>
							</montant>
						</montant>
					</remuneration>
					<dateDebut>01/2023</dateDebut>
					<dateFin>12/2023</dateFin>
				</items>
			</items>
			<neant>false</neant>
		</activProfCinqDerniereDto>
		<activProfConjointDto>
			<neant>true</neant>
		</activProfConjointDto>
		<fonctionBenevoleDto>
			<items/>
			<neant>true</neant>
		</fonctionBenevoleDto>
		<mandatElectifDto>
			<items>
				<items>
					<motif>
						<id>CREATION</id>
						<label/>
					</motif>
					<commentaire>Fin de mandat de Conseiller D&#xe9;partemental - juin 2021</commentaire>
					<conservee>true</conservee>
					<descriptionMandat>Conseiller D&#xe9;partemental</descriptionMandat>
					<remuneration>
						<brutNet>Net</brutNet>
						<montant>
							<montant>
								<annee>2021</annee>
								<montant>15 402</montant>
							</montant>
						</montant>
					</remuneration>
					<dateDebut>01/2021</dateDebut>
					<dateFin>06/2021</dateFin>
				</items>
				<items>
					<motif>
						<id>CREATION</id>
						<label/>
					</motif>
					<commentaire/>
					<descriptionMandat>d&#xe9;put&#xe9;</descriptionMandat>
					<remuneration>
						<brutNet>Net</brutNet>
						<montant>
							<montant>
								<annee>2017</annee>
								<montant>31 114</montant>
							</montant>
							<montant>
								<annee>2018</annee>
								<montant>71 041</montant>
							</montant>
							<montant>
								<annee>2019</annee>
								<montant>71 104</montant>
							</montant>
							<montant>
								<annee>2020</annee>
								<montant>70 773</montant>
							</montant>
							<montant>
								<annee>2021</annee>
								<montant>70 676</montant>
							</montant>
							<montant>
								<annee>2022</annee>
								<montant>35 338</montant>
							</montant>
						</montant>
					</remuneration>
					<dateDebut>06/2017</dateDebut>
					<dateFin>06/2022</dateFin>
				</items>
			</items>
			<neant>false</neant>
		</mandatElectifDto>
		<participationDirigeantDto>
			<items>
				<items>
					<motif>
						<id>CREATION</id>
						<label/>
					</motif>
					<commentaire>Fin de mandat de Pr&#xe9;sident du Pays de Foug&#xe8;res le 5 juillet 2021</commentaire>
					<conservee>true</conservee>
					<nomSociete>Association Pays de Foug&#xe8;res en marche</nomSociete>
					<activite>Pr&#xe9;sident</activite>
					<remuneration>
						<brutNet>Net</brutNet>
						<montant>
							<montant>
								<annee>2012</annee>
								<montant>0</montant>
							</montant>
							<montant>
								<annee>2013</annee>
								<montant>0</montant>
							</montant>
							<montant>
								<annee>2014</annee>
								<montant>0</montant>
							</montant>
							<montant>
								<annee>2015</annee>
								<montant>0</montant>
							</montant>
							<montant>
								<annee>2016</annee>
								<montant>0</montant>
							</montant>
							<montant>
								<annee>2017</annee>
								<montant>0</montant>
							</montant>
							<montant>
								<annee>2018</annee>
								<montant>0</montant>
							</montant>
							<montant>
								<annee>2019</annee>
								<montant>0</montant>
							</montant>
							<montant>
								<annee>2020</annee>
								<montant>0</montant>
							</montant>
							<montant>
								<annee>2021</annee>
								<montant>0</montant>
							</montant>
						</montant>
					</remuneration>
					<dateDebut>01/2012</dateDebut>
					<dateFin>07/2021</dateFin>
				</items>
				<items>
					<motif>
						<id>CREATION</id>
						<label/>
					</motif>
					<commentaire>Fin de repr&#xe9;sentant au titre du Conseil d&#xe9;partemental d&apos;Ille-et-Vilaine au 27 juin 2021</commentaire>
					<conservee>true</conservee>
					<nomSociete>Coll&#xe8;ge Sainte Marie</nomSociete>
					<activite>Membre du Conseil d&apos;administration</activite>
					<remuneration>
						<brutNet>Net</brutNet>
						<montant>
							<montant>
								<annee>2021</annee>
								<montant>0</montant>
							</montant>
						</montant>
					</remuneration>
					<dateDebut>01/2021</dateDebut>
					<dateFin>06/2021</dateFin>
				</items>
				<items>
					<motif>
						<id>CREATION</id>
						<label/>
					</motif>
					<commentaire>Fin  de repr&#xe9;sentation au titre du Conseil d&#xe9;partemental d&apos;Ille-et-Vilaine - fin de mandat juin 2021</commentaire>
					<conservee>true</conservee>
					<nomSociete>Coll&#xe8;ge Th&#xe9;r&#xe8;se-Pierre</nomSociete>
					<activite>Membre du Conseil d&apos;administration</activite>
					<remuneration>
						<brutNet>Net</brutNet>
						<montant>
							<montant>
								<annee>2021</annee>
								<montant>0</montant>
							</montant>
						</montant>
					</remuneration>
					<dateDebut>01/2021</dateDebut>
					<dateFin>06/2021</dateFin>
				</items>
				<items>
					<motif>
						<id>CREATION</id>
						<label/>
					</motif>
					<commentaire>Fin  de repr&#xe9;sentation au titre du Conseil d&#xe9;partemental d&apos;Ille-et-Vilaine - fin de mandat juin 2021</commentaire>
					<conservee>true</conservee>
					<nomSociete>ape2A</nomSociete>
					<activite>Membre du Conseil d&apos;administration</activite>
					<remuneration>
						<brutNet>Net</brutNet>
						<montant>
							<montant>
								<annee>2021</annee>
								<montant>0</montant>
							</montant>
						</montant>
					</remuneration>
					<dateDebut>01/2021</dateDebut>
					<dateFin>06/2021</dateFin>
				</items>
				<items>
					<motif>
						<id>CREATION</id>
						<label/>
					</motif>
					<commentaire>Fin  de repr&#xe9;sentation au titre du Conseil d&#xe9;partemental d&apos;Ille-et-Vilaine - fin de mandat juin 2021</commentaire>
					<conservee>true</conservee>
					<nomSociete>Association Le Parc</nomSociete>
					<activite>Membre du Conseil d&apos;administration</activite>
					<remuneration>
						<brutNet>Net</brutNet>
						<montant>
							<montant>
								<annee>2021</annee>
								<montant>0</montant>
							</montant>
						</montant>
					</remuneration>
					<dateDebut>01/2021</dateDebut>
					<dateFin>06/2021</dateFin>
				</items>
				<items>
					<motif>
						<id>CREATION</id>
						<label/>
					</motif>
					<commentaire>Fin  de repr&#xe9;sentation au titre du Conseil d&#xe9;partemental d&apos;Ille-et-Vilaine - fin de mandat juin 2021</commentaire>
					<conservee>true</conservee>
					<nomSociete>Clic CAUDHEM</nomSociete>
					<activite>Membre du Conseil d&apos;administration</activite>
					<remuneration>
						<brutNet>Net</brutNet>
						<montant>
							<montant>
								<annee>2021</annee>
								<montant>0</montant>
							</montant>
						</montant>
					</remuneration>
					<dateDebut>01/2021</dateDebut>
					<dateFin>06/2021</dateFin>
				</items>
				<items>
					<motif>
						<id>CREATION</id>
						<label/>
					</motif>
					<commentaire>Fin  de repr&#xe9;sentation au titre du Conseil d&#xe9;partemental d&apos;Ille-et-Vilaine - fin de mandat juin 2021</commentaire>
					<conservee>true</conservee>
					<nomSociete>Pays d&apos;accueil Touristique</nomSociete>
					<activite>Membre du Conseil d&apos;administration</activite>
					<remuneration>
						<brutNet>Net</brutNet>
						<montant>
							<montant>
								<annee>2021</annee>
								<montant>0</montant>
							</montant>
						</montant>
					</remuneration>
					<dateDebut>01/2021</dateDebut>
					<dateFin>06/2021</dateFin>
				</items>
				<items>
					<motif>
						<id>CREATION</id>
						<label/>
					</motif>
					<commentaire>Fin  de repr&#xe9;sentation au titre du Conseil d&#xe9;partemental d&apos;Ille-et-Vilaine - fin de mandat juin 2021</commentaire>
					<conservee>true</conservee>
					<nomSociete>Association la Dusseti&#xe8;re</nomSociete>
					<activite>Membre du Conseil d&apos;administration</activite>
					<remuneration>
						<brutNet>Net</brutNet>
						<montant>
							<montant>
								<annee>2021</annee>
								<montant>0</montant>
							</montant>
						</montant>
					</remuneration>
					<dateDebut>01/2021</dateDebut>
					<dateFin>06/2021</dateFin>
				</items>
				<items>
					<motif>
						<id>CREATION</id>
						<label/>
					</motif>
					<commentaire>Fin  de repr&#xe9;sentation au titre du Conseil d&#xe9;partemental d&apos;Ille-et-Vilaine - fin de mandat juin 2021</commentaire>
					<conservee>true</conservee>
					<nomSociete>LABOCEA</nomSociete>
					<activite>Membre du Conseil d&apos;administration</activite>
					<remuneration>
						<brutNet>Net</brutNet>
						<montant>
							<montant>
								<annee>2021</annee>
								<montant>0</montant>
							</montant>
						</montant>
					</remuneration>
					<dateDebut>01/2021</dateDebut>
					<dateFin>06/2021</dateFin>
				</items>
				<items>
					<motif>
						<id>CREATION</id>
						<label/>
					</motif>
					<commentaire/>
					<conservee>true</conservee>
					<nomSociete>Association LA DUSSETIERE</nomSociete>
					<activite>Membre du conseil d&apos;administration</activite>
					<remuneration>
						<brutNet>Net</brutNet>
						<montant>
							<montant>
								<annee>2022</annee>
								<montant>0</montant>
							</montant>
						</montant>
					</remuneration>
					<dateDebut>07/2022</dateDebut>
					<dateFin/>
				</items>
				<items>
					<motif>
						<id>CREATION</id>
						<label/>
					</motif>
					<commentaire/>
					<conservee>true</conservee>
					<nomSociete>POSABITAT</nomSociete>
					<activite>Membre du conseil d&apos;administration</activite>
					<remuneration>
						<brutNet>Net</brutNet>
						<montant>
							<montant>
								<annee>2022</annee>
								<montant>0</montant>
							</montant>
						</montant>
					</remuneration>
					<dateDebut>05/2022</dateDebut>
					<dateFin/>
				</items>
			</items>
			<neant>false</neant>
		</participationDirigeantDto>
		<participationFinanciereDto>
			<items/>
			<neant>true</neant>
		</participationFinanciereDto>
		<activCollaborateursDto>
			<items>
				<items>
					<motif>
						<id>CREATION</id>
						<label/>
					</motif>
					<commentaire/>
					<nom>DUBOIS Florence</nom>
					<employeur/>
					<descriptionActivite>Assistante parlementaire</descriptionActivite>
				</items>
				<items>
					<motif>
						<id>CREATION</id>
						<label/>
					</motif>
					<commentaire/>
					<nom>GOURET Ulysse</nom>
					<employeur/>
					<descriptionActivite>Assistant parlementaire</descriptionActivite>
				</items>
				<items>
					<motif>
						<id>CREATION</id>
						<label/>
					</motif>
					<commentaire/>
					<nom>CHARON Franck</nom>
					<employeur/>
					<descriptionActivite>Assistant parlementaire</descriptionActivite>
				</items>
			</items>
			<neant>false</neant>
		</activCollaborateursDto>
		<observationInteretDto>
			<neant>true</neant>
		</observationInteretDto>
		<general>
			<typeDeclaration>
				<id>DIA</id>
				<label>D&#xe9;claration d&apos;int&#xe9;r&#xea;ts et d&apos;activit&#xe9;s</label>
			</typeDeclaration>
			<mandat>
				<label>D&#xe9;put&#xe9; ou s&#xe9;nateur</label>
			</mandat>
			<qualiteMandat>
				<typeMandat>D&#xe9;put&#xe9;</typeMandat>
				<codCategorieMandat>PAR</codCategorieMandat>
				<nomCategorieMandat>D&#xe9;put&#xe9; ou s&#xe9;nateur</nomCategorieMandat>
				<codTypeMandatFichier>depute</codTypeMandatFichier>
				<labelTypeMandat>D&#xe9;put&#xe9;</labelTypeMandat>
				<labelOrgane>D&#xe9;partement d&apos;&#xe9;lection</labelOrgane>
				<codeListeOrgane>ZEP</codeListeOrgane>
			</qualiteMandat>
			<organe>
				<codeOrgane>35</codeOrgane>
				<codeListeOrgane>ZEP</codeListeOrgane>
				<nomListeOrgane>Zones d&apos;&#xe9;lection des parlementaires</nomListeOrgane>
				<labelOrgane>Ille-et-Vilaine(35)</labelOrgane>
				<labelDeclaration/>
				<organeParent/>
				<horsLoi3DS>false</horsLoi3DS>
			</organe>
			<qualiteDeclarant/>
			<qualiteDeclarantForPDF>D&#xe9;put&#xe9;/Ille-et-Vilaine(35)</qualiteDeclarantForPDF>
			<dateDebutMandat>07/07/2024</dateDebutMandat>
			<dateFinMandat/>
			<dateDernDeclar/>
			<regimeMatrimonial/>
			<regimeMatrimonialComments/>
			<nomSociete/>
			<nomSocieteMere/>
			<chiffreAffaire/>
			<nbLogements/>
			<declarationModificative>false</declarationModificative>
			<etablissement/>
			<declarant>
				<civilite>M.</civilite>
				<nom>BENOIT</nom>
				<prenom>Thierry</prenom>
				<email>
            [Donn&#xe9;es non publi&#xe9;es]
        </email>
				<dateNaissance>13/09/1966</dateNaissance>
				<pieceIdentite/>
				<telephoneDec>
            [Donn&#xe9;es non publi&#xe9;es]
        </telephoneDec>
				<adresseDec>
					<voie>
            [Donn&#xe9;es non publi&#xe9;es]
        </voie>
					<complement>
            [Donn&#xe9;es non publi&#xe9;es]
        </complement>
					<codePostal>
            [Donn&#xe9;es non publi&#xe9;es]
        </codePostal>
					<ville>
            [Donn&#xe9;es non publi&#xe9;es]
        </ville>
					<pays>
            [Donn&#xe9;es non publi&#xe9;es]
        </pays>
				</adresseDec>
			</declarant>
		</general>
	</declaration>
<declaration>
		<dateDepot>15/11/2024 15:04:20</dateDepot>
		<uuid>275cf02c-683b-40cd-afeb-1fa4d4b668ae</uuid>
		<origine>ADEL</origine>
		<complete>true</complete>
		<attachedFiles>
			<attachedFiles>
				<fileName>VUE_PDF_DU_RECEPISSE_DU_DEPOT_XML</fileName>
				<serverFileName/>
				<base64EncodedContent/>
			</attachedFiles>
		</attachedFiles>
		<declarationVersion>20171221</declarationVersion>
		<activConsultantDto>
			<neant>true</neant>
		</activConsultantDto>
		<activProfCinqDerniereDto>
			<items>
				<items>
					<motif>
						<id>CREATION</id>
						<label/>
					</motif>
					<commentaire/>
					<conservee>true</conservee>
					<description>Vente de vins</description>
					<employeur>VINS HENRI MAIRE</employeur>
					<remuneration>
						<brutNet>Net</brutNet>
						<montant>
							<montant>
								<annee>2020</annee>
								<montant>174</montant>
							</montant>
						</montant>
					</remuneration>
					<dateDebut>01/2020</dateDebut>
					<dateFin>12/2020</dateFin>
				</items>
				<items>
					<motif>
						<id>CREATION</id>
						<label/>
					</motif>
					<commentaire/>
					<description>Repr&#xe9;sentant de commerce</description>
					<employeur>Henri MAIRE</employeur>
					<remuneration>
						<brutNet>Net</brutNet>
						<montant>
							<montant>
								<annee>2021</annee>
								<montant>228</montant>
							</montant>
						</montant>
					</remuneration>
					<dateDebut>01/2021</dateDebut>
					<dateFin>12/2021</dateFin>
				</items>
				<items>
					<motif>
						<id>CREATION</id>
						<label/>
					</motif>
					<commentaire/>
					<conservee>true</conservee>
					<description>Vente de vins</description>
					<employeur>Henri maire</employeur>
					<remuneration>
						<brutNet>Net</brutNet>
						<montant>
							<montant>
								<annee>2023</annee>
								<montant>199</montant>
							</montant>
						</montant>
					</remuneration>
					<dateDebut>01/2023</dateDebut>
					<dateFin>12/2023</dateFin>
				</items>
			</items>
			<neant>false</neant>
		</activProfCinqDerniereDto>
		<activProfConjointDto>
			<items/>
			<neant>true</neant>
		</activProfConjointDto>
		<fonctionBenevoleDto>
			<neant>true</neant>
		</fonctionBenevoleDto>
		<mandatElectifDto>
			<items>
				<items>
					<motif>
						<id>CREATION</id>
						<label/>
					</motif>
					<commentaire>Fin de mandat de Conseiller D&#xe9;partemental - juin 2021</commentaire>
					<conservee>true</conservee>
					<descriptionMandat>Conseiller D&#xe9;partemental</descriptionMandat>
					<remuneration>
						<brutNet>Net</brutNet>
						<montant>
							<montant>
								<annee>2021</annee>
								<montant>15 402</montant>
							</montant>
						</montant>
					</remuneration>
					<dateDebut>01/2021</dateDebut>
					<dateFin>06/2021</dateFin>
				</items>
				<items>
					<motif>
						<id>CREATION</id>
						<label/>
					</motif>
					<commentaire/>
					<descriptionMandat>d&#xe9;put&#xe9;</descriptionMandat>
					<remuneration>
						<brutNet>Net</brutNet>
						<montant>
							<montant>
								<annee>2017</annee>
								<montant>31 114</montant>
							</montant>
							<montant>
								<annee>2018</annee>
								<montant>71 041</montant>
							</montant>
							<montant>
								<annee>2019</annee>
								<montant>71 104</montant>
							</montant>
							<montant>
								<annee>2020</annee>
								<montant>70 773</montant>
							</montant>
							<montant>
								<annee>2021</annee>
								<montant>70 676</montant>
							</montant>
							<montant>
								<annee>2022</annee>
								<montant>35 338</montant>
							</montant>
						</montant>
					</remuneration>
					<dateDebut>06/2017</dateDebut>
					<dateFin>06/2022</dateFin>
				</items>
			</items>
			<neant>false</neant>
		</mandatElectifDto>
		<participationDirigeantDto>
			<items>
				<items>
					<motif>
						<id>CREATION</id>
						<label/>
					</motif>
					<commentaire>Fin de mandat de Pr&#xe9;sident du Pays de Foug&#xe8;res le 5 juillet 2021</commentaire>
					<conservee>true</conservee>
					<nomSociete>Association Pays de Foug&#xe8;res en marche</nomSociete>
					<activite>Pr&#xe9;sident</activite>
					<remuneration>
						<brutNet>Net</brutNet>
						<montant>
							<montant>
								<annee>2012</annee>
								<montant>0</montant>
							</montant>
							<montant>
								<annee>2013</annee>
								<montant>0</montant>
							</montant>
							<montant>
								<annee>2014</annee>
								<montant>0</montant>
							</montant>
							<montant>
								<annee>2015</annee>
								<montant>0</montant>
							</montant>
							<montant>
								<annee>2016</annee>
								<montant>0</montant>
							</montant>
							<montant>
								<annee>2017</annee>
								<montant>0</montant>
							</montant>
							<montant>
								<annee>2018</annee>
								<montant>0</montant>
							</montant>
							<montant>
								<annee>2019</annee>
								<montant>0</montant>
							</montant>
							<montant>
								<annee>2020</annee>
								<montant>0</montant>
							</montant>
							<montant>
								<annee>2021</annee>
								<montant>0</montant>
							</montant>
						</montant>
					</remuneration>
					<dateDebut>01/2012</dateDebut>
					<dateFin>07/2021</dateFin>
				</items>
				<items>
					<motif>
						<id>CREATION</id>
						<label/>
					</motif>
					<commentaire>Fin de repr&#xe9;sentant au titre du Conseil d&#xe9;partemental d&apos;Ille-et-Vilaine au 27 juin 2021</commentaire>
					<conservee>true</conservee>
					<nomSociete>Coll&#xe8;ge Sainte Marie</nomSociete>
					<activite>Membre du Conseil d&apos;administration</activite>
					<remuneration>
						<brutNet>Net</brutNet>
						<montant>
							<montant>
								<annee>2021</annee>
								<montant>0</montant>
							</montant>
						</montant>
					</remuneration>
					<dateDebut>01/2021</dateDebut>
					<dateFin>06/2021</dateFin>
				</items>
				<items>
					<motif>
						<id>CREATION</id>
						<label/>
					</motif>
					<commentaire>Fin de repr&#xe9;sentation au titre du Conseil d&#xe9;partemental d&apos;Ille-et-Vilaine - fin de mandat juin 2021</commentaire>
					<conservee>true</conservee>
					<nomSociete>Coll&#xe8;ge Th&#xe9;r&#xe8;se-Pierre</nomSociete>
					<activite>Membre du Conseil d&apos;administration</activite>
					<remuneration>
						<brutNet>Net</brutNet>
						<montant>
							<montant>
								<annee>2021</annee>
								<montant>0</montant>
							</montant>
						</montant>
					</remuneration>
					<dateDebut>01/2021</dateDebut>
					<dateFin>06/2021</dateFin>
				</items>
				<items>
					<motif>
						<id>CREATION</id>
						<label/>
					</motif>
					<commentaire>Fin de repr&#xe9;sentation au titre du Conseil d&#xe9;partemental d&apos;Ille-et-Vilaine - fin de mandat juin 2021</commentaire>
					<conservee>true</conservee>
					<nomSociete>ape2A</nomSociete>
					<activite>Membre du Conseil d&apos;administration</activite>
					<remuneration>
						<brutNet>Net</brutNet>
						<montant>
							<montant>
								<annee>2021</annee>
								<montant>0</montant>
							</montant>
						</montant>
					</remuneration>
					<dateDebut>01/2021</dateDebut>
					<dateFin>06/2021</dateFin>
				</items>
				<items>
					<motif>
						<id>CREATION</id>
						<label/>
					</motif>
					<commentaire>Fin de repr&#xe9;sentation au titre du Conseil d&#xe9;partemental d&apos;Ille-et-Vilaine - fin de mandat juin 2021</commentaire>
					<conservee>true</conservee>
					<nomSociete>Association Le Parc</nomSociete>
					<activite>Membre du Conseil d&apos;administration</activite>
					<remuneration>
						<brutNet>Net</brutNet>
						<montant>
							<montant>
								<annee>2021</annee>
								<montant>0</montant>
							</montant>
						</montant>
					</remuneration>
					<dateDebut>01/2021</dateDebut>
					<dateFin>06/2021</dateFin>
				</items>
				<items>
					<motif>
						<id>CREATION</id>
						<label/>
					</motif>
					<commentaire>Fin de repr&#xe9;sentation au titre du Conseil d&#xe9;partemental d&apos;Ille-et-Vilaine - fin de mandat juin 2021</commentaire>
					<conservee>true</conservee>
					<nomSociete>Clic CAUDHEM</nomSociete>
					<activite>Membre du Conseil d&apos;administration</activite>
					<remuneration>
						<brutNet>Net</brutNet>
						<montant>
							<montant>
								<annee>2021</annee>
								<montant>0</montant>
							</montant>
						</montant>
					</remuneration>
					<dateDebut>01/2021</dateDebut>
					<dateFin>06/2021</dateFin>
				</items>
				<items>
					<motif>
						<id>CREATION</id>
						<label/>
					</motif>
					<commentaire>Fin de repr&#xe9;sentation au titre du Conseil d&#xe9;partemental d&apos;Ille-et-Vilaine - fin de mandat juin 2021</commentaire>
					<conservee>true</conservee>
					<nomSociete>Pays d&apos;accueil Touristique</nomSociete>
					<activite>Membre du Conseil d&apos;administration</activite>
					<remuneration>
						<brutNet>Net</brutNet>
						<montant>
							<montant>
								<annee>2021</annee>
								<montant>0</montant>
							</montant>
						</montant>
					</remuneration>
					<dateDebut>01/2021</dateDebut>
					<dateFin>06/2021</dateFin>
				</items>
				<items>
					<motif>
						<id>CREATION</id>
						<label/>
					</motif>
					<commentaire>Fin de repr&#xe9;sentation au titre du Conseil d&#xe9;partemental d&apos;Ille-et-Vilaine - fin de mandat juin 2021</commentaire>
					<conservee>true</conservee>
					<nomSociete>Association la Dusseti&#xe8;re</nomSociete>
					<activite>Membre du Conseil d&apos;administration</activite>
					<remuneration>
						<brutNet>Net</brutNet>
						<montant>
							<montant>
								<annee>2021</annee>
								<montant>0</montant>
							</montant>
						</montant>
					</remuneration>
					<dateDebut>01/2021</dateDebut>
					<dateFin>06/2021</dateFin>
				</items>
				<items>
					<motif>
						<id>CREATION</id>
						<label/>
					</motif>
					<commentaire>Fin de repr&#xe9;sentation au titre du Conseil d&#xe9;partemental d&apos;Ille-et-Vilaine - fin de mandat juin 2021</commentaire>
					<conservee>true</conservee>
					<nomSociete>LABOCEA</nomSociete>
					<activite>Membre du Conseil d&apos;administration</activite>
					<remuneration>
						<brutNet>Net</brutNet>
						<montant>
							<montant>
								<annee>2021</annee>
								<montant>0</montant>
							</montant>
						</montant>
					</remuneration>
					<dateDebut>01/2021</dateDebut>
					<dateFin>06/2021</dateFin>
				</items>
				<items>
					<motif>
						<id>CREATION</id>
						<label/>
					</motif>
					<commentaire/>
					<conservee>true</conservee>
					<nomSociete>Association LA DUSSETIERE</nomSociete>
					<activite>Membre du conseil d&apos;administration</activite>
					<remuneration>
						<brutNet>Net</brutNet>
						<montant>
							<montant>
								<annee>2022</annee>
								<montant>0</montant>
							</montant>
						</montant>
					</remuneration>
					<dateDebut>07/2022</dateDebut>
					<dateFin/>
				</items>
				<items>
					<motif>
						<id>CREATION</id>
						<label/>
					</motif>
					<commentaire/>
					<conservee>true</conservee>
					<nomSociete>POSABITAT</nomSociete>
					<activite>Membre du conseil d&apos;administration</activite>
					<remuneration>
						<brutNet>Net</brutNet>
						<montant>
							<montant>
								<annee>2022</annee>
								<montant>0</montant>
							</montant>
						</montant>
					</remuneration>
					<dateDebut>05/2022</dateDebut>
					<dateFin/>
				</items>
				<items>
					<motif>
						<id>CREATION</id>
						<label/>
					</motif>
					<commentaire>Je suis d&#xe9;sign&#xe9; g&#xe9;rant de la SCI</commentaire>
					<conservee>true</conservee>
					<nomSociete>SCI 
        [Donn&#xe9;es non publi&#xe9;es]
    </nomSociete>
					<activite>SCI</activite>
					<remuneration>
						<brutNet>Net</brutNet>
						<montant>
							<montant>
								<annee>2022</annee>
								<montant>0</montant>
							</montant>
							<montant>
								<annee>2023</annee>
								<montant>0</montant>
							</montant>
							<montant>
								<annee>2024</annee>
								<montant>0</montant>
							</montant>
						</montant>
					</remuneration>
					<dateDebut>10/2022</dateDebut>
					<dateFin>07/2024</dateFin>
				</items>
			</items>
			<neant>false</neant>
		</participationDirigeantDto>
		<participationFinanciereDto>
			<items>
				<items>
					<motif>
						<id>CREATION</id>
						<label/>
					</motif>
					<commentaire>Je n&apos;ai per&#xe7;u aucune r&#xe9;mun&#xe9;ration ni gratification</commentaire>
					<nomSociete>SCI 
        [Donn&#xe9;es non publi&#xe9;es]
    </nomSociete>
					<evaluation>197880</evaluation>
					<remuneration>0</remuneration>
					<capitalDetenu>75</capitalDetenu>
					<nombreParts>19788</nombreParts>
					<actiConseil>Non</actiConseil>
				</items>
			</items>
			<neant>false</neant>
		</participationFinanciereDto>
		<activCollaborateursDto>
			<items>
				<items>
					<motif>
						<id>CREATION</id>
						<label/>
					</motif>
					<commentaire/>
					<nom>DUBOIS Florence</nom>
					<employeur/>
					<descriptionActivite>Assistante parlementaire</descriptionActivite>
				</items>
				<items>
					<motif>
						<id>CREATION</id>
						<label/>
					</motif>
					<commentaire/>
					<nom>CHARON Franck</nom>
					<employeur/>
					<descriptionActivite>Assistant parlementaire</descriptionActivite>
				</items>
			</items>
			<neant>false</neant>
		</activCollaborateursDto>
		<observationInteretDto>
			<neant>true</neant>
		</observationInteretDto>
		<general>
			<typeDeclaration>
				<id>DIA</id>
				<label>D&#xe9;claration d&apos;int&#xe9;r&#xea;ts et d&apos;activit&#xe9;s modificative</label>
				<filtre/>
			</typeDeclaration>
			<mandat>
				<label>D&#xe9;put&#xe9; ou s&#xe9;nateur</label>
			</mandat>
			<qualiteMandat>
				<typeMandat>D&#xe9;put&#xe9;</typeMandat>
				<codCategorieMandat>PAR</codCategorieMandat>
				<nomCategorieMandat>D&#xe9;put&#xe9; ou s&#xe9;nateur</nomCategorieMandat>
				<codTypeMandatFichier>depute</codTypeMandatFichier>
				<labelTypeMandat>D&#xe9;put&#xe9;</labelTypeMandat>
				<labelOrgane>D&#xe9;partement d&apos;&#xe9;lection</labelOrgane>
				<codeListeOrgane>ZEP</codeListeOrgane>
			</qualiteMandat>
			<organe/>
			<qualiteDeclarant/>
			<qualiteDeclarantForPDF>D&#xe9;put&#xe9;</qualiteDeclarantForPDF>
			<dateDebutMandat>07/07/2024</dateDebutMandat>
			<dateFinMandat/>
			<dateDernDeclar/>
			<regimeMatrimonial/>
			<regimeMatrimonialComments/>
			<nomSociete/>
			<nomSocieteMere/>
			<chiffreAffaire/>
			<nbLogements/>
			<declarationModificative>true</declarationModificative>
			<etablissement/>
			<declarant>
				<civilite>M.</civilite>
				<nom>BENOIT</nom>
				<prenom>Thierry</prenom>
				<email>
            [Donn&#xe9;es non publi&#xe9;es]
        </email>
				<dateNaissance>13/09/1966</dateNaissance>
				<pieceIdentite/>
				<telephoneDec>
            [Donn&#xe9;es non publi&#xe9;es]
        </telephoneDec>
				<adresseDec>
					<voie>
            [Donn&#xe9;es non publi&#xe9;es]
        </voie>
					<complement>
            [Donn&#xe9;es non publi&#xe9;es]
        </complement>
					<codePostal>
            [Donn&#xe9;es non publi&#xe9;es]
        </codePostal>
					<ville>
            [Donn&#xe9;es non publi&#xe9;es]
        </ville>
					<pays>
            [Donn&#xe9;es non publi&#xe9;es]
        </pays>
				</adresseDec>
			</declarant>
		</general>
	</declaration>