<declaration>
		<dateDepot>31/03/2025 20:48:29</dateDepot>
		<uuid>dbb13c2a-283a-4dbd-8af6-ac5fb3001c1a</uuid>
		<origine>ADEL</origine>
		<complete>true</complete>
		<attachedFiles>
			<attachedFiles>
				<fileName>VUE_PDF_DU_RECEPISSE_DU_DEPOT_XML</fileName>
				<serverFileName/>
				<base64EncodedContent/>
			</attachedFiles>
		</attachedFiles>
		<declarationVersion>20171221</declarationVersion>
		<activConsultantDto>
			<items/>
			<neant>true</neant>
		</activConsultantDto>
		<activProfCinqDerniereDto>
			<items>
				<items>
					<motif>
						<id>CREATION</id>
						<label/>
					</motif>
					<commentaire>N&#xe9;ant</commentaire>
					<description>N&#xe9;ant</description>
					<employeur>N&#xe9;ant</employeur>
					<remuneration>
						<brutNet>Net</brutNet>
						<montant>
							<montant>
								<annee>2020</annee>
								<montant>0</montant>
							</montant>
							<montant>
								<annee>2021</annee>
								<montant>0</montant>
							</montant>
							<montant>
								<annee>2022</annee>
								<montant>0</montant>
							</montant>
							<montant>
								<annee>2023</annee>
								<montant>0</montant>
							</montant>
							<montant>
								<annee>2024</annee>
								<montant>0</montant>
							</montant>
							<montant>
								<annee>2025</annee>
								<montant>0</montant>
							</montant>
						</montant>
					</remuneration>
					<dateDebut>03/2020</dateDebut>
					<dateFin>03/2025</dateFin>
				</items>
			</items>
			<neant>false</neant>
		</activProfCinqDerniereDto>
		<activProfConjointDto>
			<items>
				<items>
					<motif>
						<id>CREATION</id>
						<label/>
					</motif>
					<commentaire/>
					<nomConjoint>
            [Donn&#xe9;es non publi&#xe9;es]
        </nomConjoint>
					<employeurConjoint>Institut Vancauwenberghe 
        [Donn&#xe9;es non publi&#xe9;es]
    </employeurConjoint>
					<activiteProf>Aide Soignante 
        [Donn&#xe9;es non publi&#xe9;es]
    </activiteProf>
				</items>
			</items>
			<neant>false</neant>
		</activProfConjointDto>
		<fonctionBenevoleDto>
			<neant>true</neant>
		</fonctionBenevoleDto>
		<mandatElectifDto>
			<items>
				<items>
					<motif>
						<id>CREATION</id>
						<label/>
					</motif>
					<commentaire>Conseiller d&#xe9;partemental du canton de Dunkerque 02</commentaire>
					<conservee>true</conservee>
					<descriptionMandat>Conseiller D&#xe9;partemental du Nord</descriptionMandat>
					<remuneration>
						<brutNet>Net</brutNet>
						<montant>
							<montant>
								<annee>2019</annee>
								<montant>21 606</montant>
							</montant>
							<montant>
								<annee>2020</annee>
								<montant>21 606</montant>
							</montant>
							<montant>
								<annee>2021</annee>
								<montant>21 768</montant>
							</montant>
							<montant>
								<annee>2022</annee>
								<montant>25 065</montant>
							</montant>
							<montant>
								<annee>2023</annee>
								<montant>26 662</montant>
							</montant>
							<montant>
								<annee>2024</annee>
								<montant>26 044</montant>
							</montant>
							<montant>
								<annee>2025</annee>
								<montant>6 489</montant>
							</montant>
						</montant>
					</remuneration>
					<dateDebut>01/2019</dateDebut>
					<dateFin>03/2025</dateFin>
				</items>
				<items>
					<motif>
						<id>CREATION</id>
						<label/>
					</motif>
					<commentaire>Suivant &#xe9;lection du 08/07/2024</commentaire>
					<descriptionMandat>D&#xe9;put&#xe9;</descriptionMandat>
					<remuneration>
						<brutNet>Net</brutNet>
						<montant>
							<montant>
								<annee>2019</annee>
								<montant>71 105</montant>
							</montant>
							<montant>
								<annee>2020</annee>
								<montant>70 773</montant>
							</montant>
							<montant>
								<annee>2021</annee>
								<montant>70 676</montant>
							</montant>
							<montant>
								<annee>2022</annee>
								<montant>71 912</montant>
							</montant>
							<montant>
								<annee>2023</annee>
								<montant>73 698</montant>
							</montant>
							<montant>
								<annee>2024</annee>
								<montant>55 629</montant>
							</montant>
						</montant>
					</remuneration>
					<dateDebut>01/2019</dateDebut>
					<dateFin>09/2024</dateFin>
				</items>
				<items>
					<motif>
						<id>CREATION</id>
						<label/>
					</motif>
					<commentaire/>
					<descriptionMandat>Ministre</descriptionMandat>
					<remuneration>
						<brutNet>Net</brutNet>
						<montant>
							<montant>
								<annee>2024</annee>
								<montant>30 368</montant>
							</montant>
						</montant>
					</remuneration>
					<dateDebut>09/2024</dateDebut>
					<dateFin>12/2024</dateFin>
				</items>
				<items>
					<motif>
						<id>CREATION</id>
						<label/>
					</motif>
					<commentaire/>
					<conservee>true</conservee>
					<descriptionMandat>D&#xe9;put&#xe9;</descriptionMandat>
					<remuneration>
						<brutNet>Net</brutNet>
						<montant>
							<montant>
								<annee>2025</annee>
								<montant>13 875</montant>
							</montant>
						</montant>
					</remuneration>
					<dateDebut>01/2025</dateDebut>
					<dateFin>03/2025</dateFin>
				</items>
			</items>
			<neant>false</neant>
		</mandatElectifDto>
		<participationDirigeantDto>
			<items>
				<items>
					<motif>
						<id>CREATION</id>
						<label/>
					</motif>
					<commentaire>Renouvellement suivant d&#xe9;signation par le Conseil d&#xe9;partemental du Nord en date du 19/07/2021</commentaire>
					<conservee>true</conservee>
					<nomSociete>Grand Port Maritime de Dunkerque</nomSociete>
					<activite>Membre du conseil de d&#xe9;veloppement</activite>
					<remuneration>
						<brutNet>Net</brutNet>
						<montant>
							<montant>
								<annee>2019</annee>
								<montant>0</montant>
							</montant>
							<montant>
								<annee>2020</annee>
								<montant>0</montant>
							</montant>
							<montant>
								<annee>2021</annee>
								<montant>0</montant>
							</montant>
							<montant>
								<annee>2022</annee>
								<montant>0</montant>
							</montant>
							<montant>
								<annee>2023</annee>
								<montant>0</montant>
							</montant>
							<montant>
								<annee>2024</annee>
								<montant>0</montant>
							</montant>
							<montant>
								<annee>2025</annee>
								<montant>0</montant>
							</montant>
						</montant>
					</remuneration>
					<dateDebut>01/2019</dateDebut>
					<dateFin/>
				</items>
				<items>
					<motif>
						<id>CREATION</id>
						<label/>
					</motif>
					<commentaire>Renouvellement suivant d&#xe9;signation par le Conseil d&#xe9;partemental du Nord en date du 27/08/2021</commentaire>
					<nomSociete>Commission Locale d&apos;Information du CNPE de Gravelines</nomSociete>
					<activite>Pr&#xe9;sident</activite>
					<remuneration>
						<brutNet>Net</brutNet>
						<montant>
							<montant>
								<annee>2019</annee>
								<montant>0</montant>
							</montant>
							<montant>
								<annee>2020</annee>
								<montant>0</montant>
							</montant>
							<montant>
								<annee>2021</annee>
								<montant>0</montant>
							</montant>
							<montant>
								<annee>2022</annee>
								<montant>0</montant>
							</montant>
							<montant>
								<annee>2023</annee>
								<montant>0</montant>
							</montant>
							<montant>
								<annee>2024</annee>
								<montant>0</montant>
							</montant>
						</montant>
					</remuneration>
					<dateDebut>01/2019</dateDebut>
					<dateFin/>
				</items>
				<items>
					<motif>
						<id>CREATION</id>
						<label/>
					</motif>
					<commentaire>Renouvellement suivant d&#xe9;signation par le Conseil d&#xe9;partemental du Nord en date du 19/07/2021</commentaire>
					<nomSociete>Conseil des rivages Manche mer du nord</nomSociete>
					<activite>Membre du conseil d&apos;administration</activite>
					<remuneration>
						<brutNet>Net</brutNet>
						<montant>
							<montant>
								<annee>2019</annee>
								<montant>0</montant>
							</montant>
							<montant>
								<annee>2020</annee>
								<montant>0</montant>
							</montant>
							<montant>
								<annee>2021</annee>
								<montant>0</montant>
							</montant>
							<montant>
								<annee>2022</annee>
								<montant>0</montant>
							</montant>
							<montant>
								<annee>2023</annee>
								<montant>0</montant>
							</montant>
							<montant>
								<annee>2024</annee>
								<montant>0</montant>
							</montant>
						</montant>
					</remuneration>
					<dateDebut>01/2019</dateDebut>
					<dateFin/>
				</items>
				<items>
					<motif>
						<id>CREATION</id>
						<label/>
					</motif>
					<commentaire>Membre suppl&#xe9;ant suivant d&#xe9;signation par le Conseil d&#xe9;partemental du Nord en date 01/07/2021</commentaire>
					<nomSociete>Service D&#xe9;partemental d&apos;Incendie et de Secours du Nord</nomSociete>
					<activite>Membre du conseil d&apos;administration</activite>
					<remuneration>
						<brutNet>Net</brutNet>
						<montant>
							<montant>
								<annee>2019</annee>
								<montant>0</montant>
							</montant>
							<montant>
								<annee>2020</annee>
								<montant>0</montant>
							</montant>
							<montant>
								<annee>2021</annee>
								<montant>0</montant>
							</montant>
							<montant>
								<annee>2022</annee>
								<montant>0</montant>
							</montant>
							<montant>
								<annee>2023</annee>
								<montant>0</montant>
							</montant>
							<montant>
								<annee>2024</annee>
								<montant>0</montant>
							</montant>
						</montant>
					</remuneration>
					<dateDebut>01/2019</dateDebut>
					<dateFin/>
				</items>
				<items>
					<motif>
						<id>CREATION</id>
						<label/>
					</motif>
					<commentaire>Renouvellement suivant d&#xe9;signation par le Conseil d&#xe9;partemental du Nord en date du 19/07/2021</commentaire>
					<nomSociete>P&#xf4;le M&#xe9;tropolitain de la C&#xf4;te d&apos;Opale</nomSociete>
					<activite>Membre du conseil d&apos;administration</activite>
					<remuneration>
						<brutNet>Net</brutNet>
						<montant>
							<montant>
								<annee>2019</annee>
								<montant>0</montant>
							</montant>
							<montant>
								<annee>2020</annee>
								<montant>0</montant>
							</montant>
							<montant>
								<annee>2021</annee>
								<montant>0</montant>
							</montant>
							<montant>
								<annee>2022</annee>
								<montant>0</montant>
							</montant>
							<montant>
								<annee>2023</annee>
								<montant>0</montant>
							</montant>
							<montant>
								<annee>2024</annee>
								<montant>0</montant>
							</montant>
						</montant>
					</remuneration>
					<dateDebut>01/2019</dateDebut>
					<dateFin/>
				</items>
				<items>
					<motif>
						<id>CREATION</id>
						<label/>
					</motif>
					<commentaire>Membre suppl&#xe9;ant suivant d&#xe9;signation par le Conseil d&#xe9;partemental du Nord en date du 19/07/2021</commentaire>
					<nomSociete>CDPENAF Nord</nomSociete>
					<activite>Membre de la commission</activite>
					<remuneration>
						<brutNet>Net</brutNet>
						<montant>
							<montant>
								<annee>2019</annee>
								<montant>0</montant>
							</montant>
							<montant>
								<annee>2020</annee>
								<montant>0</montant>
							</montant>
							<montant>
								<annee>2021</annee>
								<montant>0</montant>
							</montant>
							<montant>
								<annee>2022</annee>
								<montant>0</montant>
							</montant>
							<montant>
								<annee>2023</annee>
								<montant>0</montant>
							</montant>
							<montant>
								<annee>2024</annee>
								<montant>0</montant>
							</montant>
						</montant>
					</remuneration>
					<dateDebut>01/2019</dateDebut>
					<dateFin/>
				</items>
				<items>
					<motif>
						<id>CREATION</id>
						<label/>
					</motif>
					<commentaire>Membre suppl&#xe9;ant suivant d&#xe9;signation par le Conseil d&#xe9;partemental du Nord en date du 19/07/2021</commentaire>
					<nomSociete>CODERST Nord</nomSociete>
					<activite>Membre</activite>
					<remuneration>
						<brutNet>Net</brutNet>
						<montant>
							<montant>
								<annee>2021</annee>
								<montant>0</montant>
							</montant>
							<montant>
								<annee>2022</annee>
								<montant>0</montant>
							</montant>
							<montant>
								<annee>2023</annee>
								<montant>0</montant>
							</montant>
							<montant>
								<annee>2024</annee>
								<montant>0</montant>
							</montant>
						</montant>
					</remuneration>
					<dateDebut>07/2021</dateDebut>
					<dateFin/>
				</items>
				<items>
					<motif>
						<id>CREATION</id>
						<label/>
					</motif>
					<commentaire>Renouvellement suivant d&#xe9;signation par le Conseil d&#xe9;partemental du Nord en date du 19/07/2021</commentaire>
					<nomSociete>CLE du Sage de l&apos;Yser</nomSociete>
					<activite>Pr&#xe9;sident de la commission</activite>
					<remuneration>
						<brutNet>Net</brutNet>
						<montant>
							<montant>
								<annee>2019</annee>
								<montant>0</montant>
							</montant>
							<montant>
								<annee>2020</annee>
								<montant>0</montant>
							</montant>
							<montant>
								<annee>2021</annee>
								<montant>0</montant>
							</montant>
							<montant>
								<annee>2022</annee>
								<montant>0</montant>
							</montant>
							<montant>
								<annee>2023</annee>
								<montant>0</montant>
							</montant>
							<montant>
								<annee>2024</annee>
								<montant>0</montant>
							</montant>
						</montant>
					</remuneration>
					<dateDebut>01/2019</dateDebut>
					<dateFin/>
				</items>
				<items>
					<motif>
						<id>CREATION</id>
						<label/>
					</motif>
					<commentaire>Membre d&#xe9;sign&#xe9; par le conseil d&#xe9;partemental du Nord en date du 27/09/2021</commentaire>
					<nomSociete>H&#xf4;pital maritime de Zuydcoote</nomSociete>
					<activite>Membre du Conseil de Surveillance</activite>
					<remuneration>
						<brutNet>Net</brutNet>
						<montant>
							<montant>
								<annee>2019</annee>
								<montant>0</montant>
							</montant>
							<montant>
								<annee>2020</annee>
								<montant>0</montant>
							</montant>
							<montant>
								<annee>2021</annee>
								<montant>0</montant>
							</montant>
							<montant>
								<annee>2022</annee>
								<montant>0</montant>
							</montant>
							<montant>
								<annee>2023</annee>
								<montant>0</montant>
							</montant>
							<montant>
								<annee>2024</annee>
								<montant>0</montant>
							</montant>
						</montant>
					</remuneration>
					<dateDebut>01/2019</dateDebut>
					<dateFin/>
				</items>
				<items>
					<motif>
						<id>CREATION</id>
						<label/>
					</motif>
					<commentaire>Membre d&#xe9;sign&#xe9; par le Conseil d&#xe9;partemental du Nord en date du 19/07/2021</commentaire>
					<nomSociete>Institut Vancauwenberghe de Zuydcoote</nomSociete>
					<activite>Membre du Conseil d&apos;administration</activite>
					<remuneration>
						<brutNet>Net</brutNet>
						<montant>
							<montant>
								<annee>2019</annee>
								<montant>0</montant>
							</montant>
							<montant>
								<annee>2020</annee>
								<montant>0</montant>
							</montant>
							<montant>
								<annee>2021</annee>
								<montant>0</montant>
							</montant>
							<montant>
								<annee>2022</annee>
								<montant>0</montant>
							</montant>
							<montant>
								<annee>2023</annee>
								<montant>0</montant>
							</montant>
							<montant>
								<annee>2024</annee>
								<montant>0</montant>
							</montant>
						</montant>
					</remuneration>
					<dateDebut>01/2019</dateDebut>
					<dateFin/>
				</items>
				<items>
					<motif>
						<id>CREATION</id>
						<label/>
					</motif>
					<commentaire>Membre d&#xe9;sign&#xe9; par le Conseil d&#xe9;partemental du Nord en date du 27/08/2021</commentaire>
					<nomSociete>ATP - Assembl&#xe9;e Transfrontali&#xe8;re de Partenariat associant le d&#xe9;partement du Nord</nomSociete>
					<activite>Membre</activite>
					<remuneration>
						<brutNet>Net</brutNet>
						<montant>
							<montant>
								<annee>2021</annee>
								<montant>0</montant>
							</montant>
							<montant>
								<annee>2022</annee>
								<montant>0</montant>
							</montant>
							<montant>
								<annee>2023</annee>
								<montant>0</montant>
							</montant>
							<montant>
								<annee>2024</annee>
								<montant>0</montant>
							</montant>
						</montant>
					</remuneration>
					<dateDebut>08/2021</dateDebut>
					<dateFin/>
				</items>
				<items>
					<motif>
						<id>CREATION</id>
						<label/>
					</motif>
					<commentaire>Membre d&#xe9;sign&#xe9; par le Conseil d&#xe9;partemental du Nord en date du 06/10/2021</commentaire>
					<nomSociete>CDRNM - Commission D&#xe9;partementale des Risques Naturels Majeurs</nomSociete>
					<activite>Membre</activite>
					<remuneration>
						<brutNet>Net</brutNet>
						<montant>
							<montant>
								<annee>2021</annee>
								<montant>0</montant>
							</montant>
							<montant>
								<annee>2022</annee>
								<montant>0</montant>
							</montant>
							<montant>
								<annee>2023</annee>
								<montant>0</montant>
							</montant>
							<montant>
								<annee>2024</annee>
								<montant>0</montant>
							</montant>
						</montant>
					</remuneration>
					<dateDebut>10/2021</dateDebut>
					<dateFin/>
				</items>
				<items>
					<motif>
						<id>CREATION</id>
						<label/>
					</motif>
					<commentaire>Membre d&#xe9;sign&#xe9; par le Conseil d&#xe9;partemental du Nord en date du 06/10/2021</commentaire>
					<nomSociete>CDZPCV - Commission D&#xe9;partementale de suivi sanitaire des Zones de Production de Coquillages Vivants</nomSociete>
					<activite>Membre</activite>
					<remuneration>
						<brutNet>Net</brutNet>
						<montant>
							<montant>
								<annee>2021</annee>
								<montant>0</montant>
							</montant>
							<montant>
								<annee>2022</annee>
								<montant>0</montant>
							</montant>
							<montant>
								<annee>2023</annee>
								<montant>0</montant>
							</montant>
							<montant>
								<annee>2024</annee>
								<montant>0</montant>
							</montant>
						</montant>
					</remuneration>
					<dateDebut>10/2021</dateDebut>
					<dateFin/>
				</items>
				<items>
					<motif>
						<id>CREATION</id>
						<label/>
					</motif>
					<commentaire>Membre suppl&#xe9;ant d&#xe9;sign&#xe9; par le Conseil d&#xe9;partemental du Nord en date du 06/10/2021</commentaire>
					<nomSociete>CNS FSE Comit&#xe9; National de Suivi du Fonds Social Europ&#xe9;en</nomSociete>
					<activite>Membre</activite>
					<remuneration>
						<brutNet>Net</brutNet>
						<montant>
							<montant>
								<annee>2021</annee>
								<montant>0</montant>
							</montant>
							<montant>
								<annee>2022</annee>
								<montant>0</montant>
							</montant>
							<montant>
								<annee>2023</annee>
								<montant>0</montant>
							</montant>
							<montant>
								<annee>2024</annee>
								<montant>0</montant>
							</montant>
						</montant>
					</remuneration>
					<dateDebut>10/2021</dateDebut>
					<dateFin/>
				</items>
				<items>
					<motif>
						<id>CREATION</id>
						<label/>
					</motif>
					<commentaire>Membre suppl&#xe9;ant d&#xe9;sign&#xe9; par le Conseil d&#xe9;partemental du Nord en date du 06/10/2021</commentaire>
					<nomSociete>CROPSAV Conseil R&#xe9;gional d&apos;Orientation de la Politique Sanitaire Animale et V&#xe9;g&#xe9;tale</nomSociete>
					<activite>Membre</activite>
					<remuneration>
						<brutNet>Net</brutNet>
						<montant>
							<montant>
								<annee>2021</annee>
								<montant>0</montant>
							</montant>
							<montant>
								<annee>2022</annee>
								<montant>0</montant>
							</montant>
							<montant>
								<annee>2023</annee>
								<montant>0</montant>
							</montant>
							<montant>
								<annee>2024</annee>
								<montant>0</montant>
							</montant>
						</montant>
					</remuneration>
					<dateDebut>10/2021</dateDebut>
					<dateFin/>
				</items>
				<items>
					<motif>
						<id>CREATION</id>
						<label/>
					</motif>
					<commentaire>Membre d&#xe9;sign&#xe9; par le Conseil d&#xe9;partemental du Nord en date du 19/07/2021</commentaire>
					<nomSociete>CLE du Sage du delta de l&apos;AA</nomSociete>
					<activite>Membre</activite>
					<remuneration>
						<brutNet>Net</brutNet>
						<montant>
							<montant>
								<annee>2021</annee>
								<montant>0</montant>
							</montant>
							<montant>
								<annee>2022</annee>
								<montant>0</montant>
							</montant>
							<montant>
								<annee>2023</annee>
								<montant>0</montant>
							</montant>
							<montant>
								<annee>2024</annee>
								<montant>0</montant>
							</montant>
						</montant>
					</remuneration>
					<dateDebut>07/2021</dateDebut>
					<dateFin/>
				</items>
				<items>
					<motif>
						<id>CREATION</id>
						<label/>
					</motif>
					<commentaire>Membre d&#xe9;sign&#xe9; par le Conseil d&#xe9;partemental du Nord en date du 19/07/2021</commentaire>
					<nomSociete>CMF Conseil Maritime de Fa&#xe7;ade Manche Est - Mer du Nord</nomSociete>
					<activite>Membre</activite>
					<remuneration>
						<brutNet>Net</brutNet>
						<montant>
							<montant>
								<annee>2021</annee>
								<montant>0</montant>
							</montant>
							<montant>
								<annee>2022</annee>
								<montant>0</montant>
							</montant>
							<montant>
								<annee>2023</annee>
								<montant>0</montant>
							</montant>
							<montant>
								<annee>2024</annee>
								<montant>0</montant>
							</montant>
						</montant>
					</remuneration>
					<dateDebut>07/2021</dateDebut>
					<dateFin/>
				</items>
				<items>
					<motif>
						<id>CREATION</id>
						<label/>
					</motif>
					<commentaire>Membre suppl&#xe9;ant d&#xe9;sign&#xe9; par le Conseil d&#xe9;partemental du Nord en date du 19/07/2021</commentaire>
					<nomSociete>Coll&#xe8;ge public du Septentrion - Bray-Dunes</nomSociete>
					<activite>Membre du conseil d&apos;administration</activite>
					<remuneration>
						<brutNet>Net</brutNet>
						<montant>
							<montant>
								<annee>2021</annee>
								<montant>0</montant>
							</montant>
							<montant>
								<annee>2022</annee>
								<montant>0</montant>
							</montant>
							<montant>
								<annee>2023</annee>
								<montant>0</montant>
							</montant>
							<montant>
								<annee>2024</annee>
								<montant>0</montant>
							</montant>
						</montant>
					</remuneration>
					<dateDebut>07/2021</dateDebut>
					<dateFin/>
				</items>
				<items>
					<motif>
						<id>CREATION</id>
						<label/>
					</motif>
					<commentaire>Membre suppl&#xe9;ant d&#xe9;sign&#xe9; par le Conseil d&#xe9;partemental du Nord en date du 19/07/2021</commentaire>
					<nomSociete>Coll&#xe8;ge public Arthur Van Hecke - Dunkerque</nomSociete>
					<activite>Membre du conseil d&apos;administration</activite>
					<remuneration>
						<brutNet>Net</brutNet>
						<montant>
							<montant>
								<annee>2021</annee>
								<montant>0</montant>
							</montant>
							<montant>
								<annee>2022</annee>
								<montant>0</montant>
							</montant>
							<montant>
								<annee>2023</annee>
								<montant>0</montant>
							</montant>
							<montant>
								<annee>2024</annee>
								<montant>0</montant>
							</montant>
						</montant>
					</remuneration>
					<dateDebut>07/2021</dateDebut>
					<dateFin/>
				</items>
				<items>
					<motif>
						<id>CREATION</id>
						<label/>
					</motif>
					<commentaire>Membre suppl&#xe9;ant d&#xe9;sign&#xe9; par le Conseil d&#xe9;partemental du Nord en date du 19/07/2021</commentaire>
					<nomSociete>Coll&#xe8;ge public Gaspard Malo - Dunkerque</nomSociete>
					<activite>Membre du conseil d&apos;administration</activite>
					<remuneration>
						<brutNet>Net</brutNet>
						<montant>
							<montant>
								<annee>2021</annee>
								<montant>0</montant>
							</montant>
							<montant>
								<annee>2022</annee>
								<montant>0</montant>
							</montant>
							<montant>
								<annee>2023</annee>
								<montant>0</montant>
							</montant>
							<montant>
								<annee>2024</annee>
								<montant>0</montant>
							</montant>
						</montant>
					</remuneration>
					<dateDebut>07/2021</dateDebut>
					<dateFin/>
				</items>
				<items>
					<motif>
						<id>CREATION</id>
						<label/>
					</motif>
					<commentaire>Membre suppl&#xe9;ant d&#xe9;sign&#xe9; par le Conseil d&#xe9;partemental du Nord en date du 19/07/2021</commentaire>
					<nomSociete>Coll&#xe8;ge public Paul Machy - Dunkerque</nomSociete>
					<activite>Membre du conseil d&apos;administration</activite>
					<remuneration>
						<brutNet>Net</brutNet>
						<montant>
							<montant>
								<annee>2021</annee>
								<montant>0</montant>
							</montant>
							<montant>
								<annee>2022</annee>
								<montant>0</montant>
							</montant>
							<montant>
								<annee>2023</annee>
								<montant>0</montant>
							</montant>
							<montant>
								<annee>2024</annee>
								<montant>0</montant>
							</montant>
						</montant>
					</remuneration>
					<dateDebut>07/2021</dateDebut>
					<dateFin/>
				</items>
				<items>
					<motif>
						<id>CREATION</id>
						<label/>
					</motif>
					<commentaire>Membre d&#xe9;sign&#xe9; par le Conseil d&#xe9;partemental du Nord en date du 19/07/2021</commentaire>
					<nomSociete>EHPAD Bray-Dunes R&#xe9;sidence Aigue Marine</nomSociete>
					<activite>Membre du conseil d&apos;administration</activite>
					<remuneration>
						<brutNet>Net</brutNet>
						<montant>
							<montant>
								<annee>2021</annee>
								<montant>0</montant>
							</montant>
							<montant>
								<annee>2022</annee>
								<montant>0</montant>
							</montant>
							<montant>
								<annee>2023</annee>
								<montant>0</montant>
							</montant>
							<montant>
								<annee>2024</annee>
								<montant>0</montant>
							</montant>
						</montant>
					</remuneration>
					<dateDebut>07/2021</dateDebut>
					<dateFin/>
				</items>
				<items>
					<motif>
						<id>CREATION</id>
						<label/>
					</motif>
					<commentaire>Membre suppl&#xe9;ant d&#xe9;sign&#xe9; par le Conseil d&#xe9;partemental du Nord en date du 08/07/2024</commentaire>
					<nomSociete>Conf&#xe9;rence permanente du tourisme</nomSociete>
					<activite>Membre du conseil d&apos;administration</activite>
					<remuneration>
						<brutNet>Net</brutNet>
						<montant>
							<montant>
								<annee>2024</annee>
								<montant>0</montant>
							</montant>
						</montant>
					</remuneration>
					<dateDebut>07/2024</dateDebut>
					<dateFin/>
				</items>
				<items>
					<motif>
						<id>CREATION</id>
						<label/>
					</motif>
					<commentaire>Membre d&#xe9;sign&#xe9; par le Conseil d&#xe9;partemental du Nord en date du 27/09/2021</commentaire>
					<nomSociete>Agate C&#xf4;te d&apos;Opale - Association de gestion des approches concertatives territoriales dans le domaine de l&apos;environnement C&#xf4;te d&apos;Opale</nomSociete>
					<activite>Vice-pr&#xe9;sident</activite>
					<remuneration>
						<brutNet>Net</brutNet>
						<montant>
							<montant>
								<annee>2021</annee>
								<montant>0</montant>
							</montant>
							<montant>
								<annee>2022</annee>
								<montant>0</montant>
							</montant>
							<montant>
								<annee>2023</annee>
								<montant>0</montant>
							</montant>
							<montant>
								<annee>2024</annee>
								<montant>0</montant>
							</montant>
						</montant>
					</remuneration>
					<dateDebut>09/2021</dateDebut>
					<dateFin/>
				</items>
				<items>
					<motif>
						<id>CREATION</id>
						<label/>
					</motif>
					<commentaire>Membre d&#xe9;sign&#xe9; par le Conseil d&#xe9;partemental du Nord en date du 27/09/2021</commentaire>
					<nomSociete>AGUR - Agence d&apos;urbanisme et de d&#xe9;veloppement de la R&#xe9;gion Flandre-Dunkerque</nomSociete>
					<activite>Membre</activite>
					<remuneration>
						<brutNet>Net</brutNet>
						<montant>
							<montant>
								<annee>2021</annee>
								<montant>0</montant>
							</montant>
							<montant>
								<annee>2022</annee>
								<montant>0</montant>
							</montant>
							<montant>
								<annee>2023</annee>
								<montant>0</montant>
							</montant>
							<montant>
								<annee>2024</annee>
								<montant>0</montant>
							</montant>
						</montant>
					</remuneration>
					<dateDebut>09/2021</dateDebut>
					<dateFin/>
				</items>
				<items>
					<motif>
						<id>CREATION</id>
						<label/>
					</motif>
					<commentaire>Membre suppl&#xe9;ant d&#xe9;sign&#xe9; par le Conseil d&#xe9;partemental du Nord en date du 27/09/2021</commentaire>
					<nomSociete>APPHF - Association des ports de plaisance maritimes et fluviaux Hauts de France</nomSociete>
					<activite>Membre</activite>
					<remuneration>
						<brutNet>Net</brutNet>
						<montant>
							<montant>
								<annee>2021</annee>
								<montant>0</montant>
							</montant>
							<montant>
								<annee>2022</annee>
								<montant>0</montant>
							</montant>
							<montant>
								<annee>2023</annee>
								<montant>0</montant>
							</montant>
							<montant>
								<annee>2024</annee>
								<montant>0</montant>
							</montant>
						</montant>
					</remuneration>
					<dateDebut>09/2021</dateDebut>
					<dateFin>06/2024</dateFin>
				</items>
				<items>
					<motif>
						<id>CREATION</id>
						<label/>
					</motif>
					<commentaire>Membre d&#xe9;sign&#xe9; par le Conseil d&#xe9;partemental du Nord en date du 27/09/2021</commentaire>
					<nomSociete>Association Rivages de France</nomSociete>
					<activite>Membre</activite>
					<remuneration>
						<brutNet>Net</brutNet>
						<montant>
							<montant>
								<annee>2021</annee>
								<montant>0</montant>
							</montant>
							<montant>
								<annee>2022</annee>
								<montant>0</montant>
							</montant>
							<montant>
								<annee>2023</annee>
								<montant>0</montant>
							</montant>
							<montant>
								<annee>2024</annee>
								<montant>0</montant>
							</montant>
						</montant>
					</remuneration>
					<dateDebut>09/2021</dateDebut>
					<dateFin/>
				</items>
				<items>
					<motif>
						<id>CREATION</id>
						<label/>
					</motif>
					<commentaire>Membre d&#xe9;sign&#xe9; par le Conseil d&#xe9;partemental du Nord en date du 27/09/2021 D&#xe9;mission suivant courrier du 10/12/2022</commentaire>
					<nomSociete>Mus&#xe9;e Portuaire</nomSociete>
					<activite>Membre du conseil d&apos;administration</activite>
					<remuneration>
						<brutNet>Net</brutNet>
						<montant>
							<montant>
								<annee>2021</annee>
								<montant>0</montant>
							</montant>
							<montant>
								<annee>2022</annee>
								<montant>0</montant>
							</montant>
						</montant>
					</remuneration>
					<dateDebut>09/2021</dateDebut>
					<dateFin>12/2022</dateFin>
				</items>
				<items>
					<motif>
						<id>CREATION</id>
						<label/>
					</motif>
					<commentaire>Membre d&#xe9;sign&#xe9; par le Conseil d&#xe9;partemental du Nord en date du 08/03/2022</commentaire>
					<nomSociete>CCM - Commission des Cultures Marines</nomSociete>
					<activite>Membre</activite>
					<remuneration>
						<brutNet>Net</brutNet>
						<montant>
							<montant>
								<annee>2022</annee>
								<montant>0</montant>
							</montant>
							<montant>
								<annee>2023</annee>
								<montant>0</montant>
							</montant>
							<montant>
								<annee>2024</annee>
								<montant>0</montant>
							</montant>
						</montant>
					</remuneration>
					<dateDebut>03/2022</dateDebut>
					<dateFin/>
				</items>
				<items>
					<motif>
						<id>CREATION</id>
						<label/>
					</motif>
					<commentaire>Membre d&#xe9;sign&#xe9; par le Conseil d&#xe9;partemental du Nord en date du 16/02/2022</commentaire>
					<nomSociete>ODPE - Observatoire D&#xe9;partemental de la Protection de l&apos;Enfance</nomSociete>
					<activite>Membre</activite>
					<remuneration>
						<brutNet>Net</brutNet>
						<montant>
							<montant>
								<annee>2022</annee>
								<montant>0</montant>
							</montant>
							<montant>
								<annee>2023</annee>
								<montant>0</montant>
							</montant>
							<montant>
								<annee>2024</annee>
								<montant>0</montant>
							</montant>
						</montant>
					</remuneration>
					<dateDebut>02/2022</dateDebut>
					<dateFin/>
				</items>
				<items>
					<motif>
						<id>CREATION</id>
						<label/>
					</motif>
					<commentaire>Membre suppl&#xe9;ant d&#xe9;sign&#xe9; par le Conseil d&#xe9;partemental du Nord en date du 21/12/2021</commentaire>
					<nomSociete>CIL - Conf&#xe9;rence intercommunale du logement</nomSociete>
					<activite>Membre</activite>
					<remuneration>
						<brutNet>Net</brutNet>
						<montant>
							<montant>
								<annee>2021</annee>
								<montant>0</montant>
							</montant>
							<montant>
								<annee>2022</annee>
								<montant>0</montant>
							</montant>
							<montant>
								<annee>2023</annee>
								<montant>0</montant>
							</montant>
							<montant>
								<annee>2024</annee>
								<montant>0</montant>
							</montant>
						</montant>
					</remuneration>
					<dateDebut>12/2021</dateDebut>
					<dateFin/>
				</items>
				<items>
					<motif>
						<id>CREATION</id>
						<label/>
					</motif>
					<commentaire>Membre d&#xe9;sign&#xe9; par le Conseil d&#xe9;partemental du Nord en date du 18/05/2022</commentaire>
					<nomSociete>CALR - Conseil acad&#xe9;mique des langues r&#xe9;gionales</nomSociete>
					<activite>Membre</activite>
					<remuneration>
						<brutNet>Net</brutNet>
						<montant>
							<montant>
								<annee>2022</annee>
								<montant>0</montant>
							</montant>
							<montant>
								<annee>2023</annee>
								<montant>0</montant>
							</montant>
							<montant>
								<annee>2024</annee>
								<montant>0</montant>
							</montant>
						</montant>
					</remuneration>
					<dateDebut>05/2022</dateDebut>
					<dateFin/>
				</items>
				<items>
					<motif>
						<id>CREATION</id>
						<label/>
					</motif>
					<commentaire>
        [Donn&#xe9;es non publi&#xe9;es]
    </commentaire>
					<nomSociete>R&#xe9;gie des ports de plaisance de Dunkerque</nomSociete>
					<activite>Membre du conseil d&apos;administration</activite>
					<remuneration>
						<brutNet>Net</brutNet>
						<montant>
							<montant>
								<annee>2016</annee>
								<montant>0</montant>
							</montant>
							<montant>
								<annee>2017</annee>
								<montant>0</montant>
							</montant>
							<montant>
								<annee>2018</annee>
								<montant>0</montant>
							</montant>
							<montant>
								<annee>2019</annee>
								<montant>0</montant>
							</montant>
							<montant>
								<annee>2020</annee>
								<montant>0</montant>
							</montant>
						</montant>
					</remuneration>
					<dateDebut>12/2016</dateDebut>
					<dateFin>06/2020</dateFin>
				</items>
			</items>
			<neant>false</neant>
		</participationDirigeantDto>
		<participationFinanciereDto>
			<items>
				<items>
					<motif>
						<id>CREATION</id>
						<label/>
					</motif>
					<commentaire/>
					<nomSociete>SCI 
        [Donn&#xe9;es non publi&#xe9;es]
    </nomSociete>
					<evaluation>150</evaluation>
					<remuneration>0</remuneration>
					<capitalDetenu>25</capitalDetenu>
					<nombreParts>1</nombreParts>
					<actiConseil>Non</actiConseil>
				</items>
				<items>
					<motif>
						<id>CREATION</id>
						<label/>
					</motif>
					<commentaire/>
					<nomSociete>SCI 
        [Donn&#xe9;es non publi&#xe9;es]
    </nomSociete>
					<evaluation>70000</evaluation>
					<remuneration>0</remuneration>
					<capitalDetenu>25</capitalDetenu>
					<nombreParts>2</nombreParts>
					<actiConseil>Non</actiConseil>
				</items>
			</items>
			<neant>false</neant>
		</participationFinanciereDto>
		<activCollaborateursDto>
			<items>
				<items>
					<motif>
						<id>CREATION</id>
						<label/>
					</motif>
					<commentaire/>
					<nom>BOULANGER Anne</nom>
					<employeur>N&#xe9;ant</employeur>
					<descriptionActivite>Collaborateur en circonscription</descriptionActivite>
				</items>
				<items>
					<motif>
						<id>CREATION</id>
						<label/>
					</motif>
					<commentaire/>
					<nom>DONNAT H&#xe9;l&#xe8;ne</nom>
					<employeur>N&#xe9;ant</employeur>
					<descriptionActivite>Directrice de cabinet Pr&#xe9;sident du groupe Horizons et ind&#xe9;pendants</descriptionActivite>
				</items>
				<items>
					<motif>
						<id>CREATION</id>
						<label/>
					</motif>
					<commentaire/>
					<nom>EVERAERE Beno&#xee;t</nom>
					<employeur>N&#xe9;ant</employeur>
					<descriptionActivite>Collaborateur en circonscription</descriptionActivite>
				</items>
				<items>
					<motif>
						<id>CREATION</id>
						<label/>
					</motif>
					<commentaire>Contrat en lien avec la pr&#xe9;sidence du groupe</commentaire>
					<nom>FLORES Lucas</nom>
					<employeur>N&#xe9;ant</employeur>
					<descriptionActivite>Collaborateur du pr&#xe9;sident du groupe Horizons et ind&#xe9;pendants</descriptionActivite>
				</items>
				<items>
					<motif>
						<id>CREATION</id>
						<label/>
					</motif>
					<commentaire>Contrat en lien avec la pr&#xe9;sidence du groupe</commentaire>
					<nom>HAFIZ Samy</nom>
					<employeur>N&#xe9;ant</employeur>
					<descriptionActivite>Collaborateur du pr&#xe9;sident du groupe Horizons et ind&#xe9;pendants</descriptionActivite>
				</items>
				<items>
					<motif>
						<id>CREATION</id>
						<label/>
					</motif>
					<commentaire/>
					<nom>SAISON Antoine</nom>
					<employeur>N&#xe9;ant</employeur>
					<descriptionActivite>Collaborateur en circonscription</descriptionActivite>
				</items>
			</items>
			<neant>false</neant>
		</activCollaborateursDto>
		<observationInteretDto>
			<neant>true</neant>
		</observationInteretDto>
		<general>
			<typeDeclaration>
				<id>DIA</id>
				<label>D&#xe9;claration d&apos;int&#xe9;r&#xea;ts et d&apos;activit&#xe9;s</label>
			</typeDeclaration>
			<mandat>
				<label>D&#xe9;put&#xe9; ou s&#xe9;nateur</label>
			</mandat>
			<qualiteMandat>
				<typeMandat>D&#xe9;put&#xe9;</typeMandat>
				<codCategorieMandat>PAR</codCategorieMandat>
				<nomCategorieMandat>D&#xe9;put&#xe9; ou s&#xe9;nateur</nomCategorieMandat>
				<codTypeMandatFichier>depute</codTypeMandatFichier>
				<labelTypeMandat>D&#xe9;put&#xe9;</labelTypeMandat>
				<labelOrgane>D&#xe9;partement d&apos;&#xe9;lection</labelOrgane>
				<codeListeOrgane>ZEP</codeListeOrgane>
			</qualiteMandat>
			<organe>
				<codeOrgane>59</codeOrgane>
				<codeListeOrgane>ZEP</codeListeOrgane>
				<nomListeOrgane>Zones d&apos;&#xe9;lection des parlementaires</nomListeOrgane>
				<labelOrgane>Nord(59)</labelOrgane>
				<labelDeclaration/>
				<organeParent/>
				<horsLoi3DS>false</horsLoi3DS>
			</organe>
			<qualiteDeclarant/>
			<qualiteDeclarantForPDF>D&#xe9;put&#xe9;/Nord(59)</qualiteDeclarantForPDF>
			<dateDebutMandat>09/07/2024</dateDebutMandat>
			<dateFinMandat/>
			<dateDernDeclar/>
			<regimeMatrimonial/>
			<regimeMatrimonialComments/>
			<nomSociete/>
			<nomSocieteMere/>
			<chiffreAffaire/>
			<nbLogements/>
			<declarationModificative>false</declarationModificative>
			<etablissement/>
			<declarant>
				<civilite>M.</civilite>
				<nom>CHRISTOPHE</nom>
				<prenom>PAUL</prenom>
				<email>
            [Donn&#xe9;es non publi&#xe9;es]
        </email>
				<dateNaissance>10/02/1971</dateNaissance>
				<pieceIdentite/>
				<telephoneDec>
            [Donn&#xe9;es non publi&#xe9;es]
        </telephoneDec>
				<adresseDec>
					<voie>
            [Donn&#xe9;es non publi&#xe9;es]
        </voie>
					<complement>
            [Donn&#xe9;es non publi&#xe9;es]
        </complement>
					<codePostal>
            [Donn&#xe9;es non publi&#xe9;es]
        </codePostal>
					<ville>
            [Donn&#xe9;es non publi&#xe9;es]
        </ville>
					<pays>
            [Donn&#xe9;es non publi&#xe9;es]
        </pays>
				</adresseDec>
			</declarant>
		</general>
	</declaration>