<declaration>
		<dateDepot>14/07/2024 19:17:57</dateDepot>
		<uuid>7d58b22c-3f26-4460-b2aa-6ac82750326d</uuid>
		<origine>ADEL</origine>
		<complete>true</complete>
		<attachedFiles>
			<attachedFiles>
				<fileName>VUE_PDF_DU_RECEPISSE_DU_DEPOT_XML</fileName>
				<serverFileName/>
				<base64EncodedContent/>
			</attachedFiles>
		</attachedFiles>
		<declarationVersion>20171221</declarationVersion>
		<activConsultantDto>
			<neant>true</neant>
		</activConsultantDto>
		<activProfCinqDerniereDto>
			<items>
				<items>
					<motif>
						<id>CREATION</id>
						<label/>
					</motif>
					<commentaire/>
					<description>enseignante chercheuse</description>
					<employeur>Minist&#xe8;re de l&apos;agriculture</employeur>
					<remuneration>
						<brutNet>Net</brutNet>
						<montant>
							<montant>
								<annee>2017</annee>
								<montant>39 300</montant>
							</montant>
							<montant>
								<annee>2018</annee>
								<montant>39 300</montant>
							</montant>
							<montant>
								<annee>2019</annee>
								<montant>45 200</montant>
							</montant>
							<montant>
								<annee>2020</annee>
								<montant>39 200</montant>
							</montant>
							<montant>
								<annee>2021</annee>
								<montant>43 500</montant>
							</montant>
							<montant>
								<annee>2022</annee>
								<montant>27 600</montant>
							</montant>
						</montant>
					</remuneration>
					<dateDebut>01/2017</dateDebut>
					<dateFin>06/2022</dateFin>
				</items>
			</items>
			<neant>false</neant>
		</activProfCinqDerniereDto>
		<activProfConjointDto>
			<items>
				<items>
					<motif>
						<id>CREATION</id>
						<label/>
					</motif>
					<commentaire/>
					<nomConjoint>
            [Donn&#xe9;es non publi&#xe9;es]
        </nomConjoint>
					<employeurConjoint>EELV</employeurConjoint>
					<activiteProf>charg&#xe9; de mission</activiteProf>
				</items>
			</items>
			<neant>false</neant>
		</activProfConjointDto>
		<fonctionBenevoleDto>
			<items>
				<items>
					<motif>
						<id>CREATION</id>
						<label/>
					</motif>
					<commentaire/>
					<conservee>true</conservee>
					<nomStructure>Membre de l&apos;acad&#xe9;mie d&apos;agriculture</nomStructure>
					<descriptionActivite>Simple membre avec participation occasionnelle &#xe0; des discussions et travaux (mise en suspend depuis le d&#xe9;but du mandat de d&#xe9;put&#xe9;e)</descriptionActivite>
				</items>
			</items>
			<neant>false</neant>
		</fonctionBenevoleDto>
		<mandatElectifDto>
			<neant>true</neant>
		</mandatElectifDto>
		<participationDirigeantDto>
			<items>
				<items>
					<motif>
						<id>CREATION</id>
						<label/>
					</motif>
					<commentaire/>
					<nomSociete>Attac</nomSociete>
					<activite>pr&#xe9;sidente</activite>
					<remuneration>
						<brutNet>Net</brutNet>
						<montant>
							<montant>
								<annee>2017</annee>
								<montant>0</montant>
							</montant>
							<montant>
								<annee>2018</annee>
								<montant>0</montant>
							</montant>
							<montant>
								<annee>2019</annee>
								<montant>0</montant>
							</montant>
							<montant>
								<annee>2020</annee>
								<montant>0</montant>
							</montant>
							<montant>
								<annee>2021</annee>
								<montant>0</montant>
							</montant>
						</montant>
					</remuneration>
					<dateDebut>06/2017</dateDebut>
					<dateFin>10/2021</dateFin>
				</items>
				<items>
					<motif>
						<id>CREATION</id>
						<label/>
					</motif>
					<commentaire/>
					<nomSociete>AgroParisTech</nomSociete>
					<activite>membre du conseil d&apos;administration</activite>
					<remuneration>
						<brutNet>Net</brutNet>
						<montant>
							<montant>
								<annee>2018</annee>
								<montant>0</montant>
							</montant>
							<montant>
								<annee>2019</annee>
								<montant>0</montant>
							</montant>
							<montant>
								<annee>2020</annee>
								<montant>0</montant>
							</montant>
							<montant>
								<annee>2021</annee>
								<montant>0</montant>
							</montant>
						</montant>
					</remuneration>
					<dateDebut>06/2018</dateDebut>
					<dateFin>06/2021</dateFin>
				</items>
				<items>
					<motif>
						<id>CREATION</id>
						<label/>
					</motif>
					<commentaire/>
					<conservee>true</conservee>
					<nomSociete>fonds de dotation de l&apos;Institut la Bo&#xe9;tie</nomSociete>
					<activite>membre du Conseil d&apos;administration</activite>
					<remuneration>
						<brutNet>Net</brutNet>
						<montant>
							<montant>
								<annee>2023</annee>
								<montant>0</montant>
							</montant>
						</montant>
					</remuneration>
					<dateDebut>06/2023</dateDebut>
					<dateFin/>
				</items>
			</items>
			<neant>false</neant>
		</participationDirigeantDto>
		<participationFinanciereDto>
			<neant>true</neant>
		</participationFinanciereDto>
		<activCollaborateursDto>
			<items>
				<items>
					<motif>
						<id>CREATION</id>
						<label/>
					</motif>
					<commentaire/>
					<nom>Am&#xe9;lie Canonne</nom>
					<employeur/>
					<descriptionActivite>collaborateur parlementaire</descriptionActivite>
				</items>
				<items>
					<motif>
						<id>CREATION</id>
						<label/>
					</motif>
					<commentaire/>
					<nom>Juliette Vellat</nom>
					<employeur/>
					<descriptionActivite>Collaborateur parlementaire</descriptionActivite>
				</items>
				<items>
					<motif>
						<id>CREATION</id>
						<label/>
					</motif>
					<commentaire/>
					<nom>Camille Labb&#xe9;</nom>
					<employeur/>
					<descriptionActivite>Collaborateur parlementaire</descriptionActivite>
				</items>
			</items>
			<neant>false</neant>
		</activCollaborateursDto>
		<observationInteretDto>
			<neant>true</neant>
		</observationInteretDto>
		<general>
			<typeDeclaration>
				<id>DIA</id>
				<label>D&#xe9;claration d&apos;int&#xe9;r&#xea;ts et d&apos;activit&#xe9;s</label>
			</typeDeclaration>
			<mandat>
				<label>D&#xe9;put&#xe9; ou s&#xe9;nateur</label>
			</mandat>
			<qualiteMandat>
				<typeMandat>D&#xe9;put&#xe9;</typeMandat>
				<codCategorieMandat>PAR</codCategorieMandat>
				<nomCategorieMandat>D&#xe9;put&#xe9; ou s&#xe9;nateur</nomCategorieMandat>
				<codTypeMandatFichier>depute</codTypeMandatFichier>
				<labelTypeMandat>D&#xe9;put&#xe9;</labelTypeMandat>
				<labelOrgane>D&#xe9;partement d&apos;&#xe9;lection</labelOrgane>
				<codeListeOrgane>ZEP</codeListeOrgane>
			</qualiteMandat>
			<organe>
				<codeOrgane>93</codeOrgane>
				<codeListeOrgane>ZEP</codeListeOrgane>
				<nomListeOrgane>Zones d&apos;&#xe9;lection des parlementaires</nomListeOrgane>
				<labelOrgane>Seine-Saint-Denis(93)</labelOrgane>
				<labelDeclaration/>
				<organeParent/>
				<horsLoi3DS>false</horsLoi3DS>
			</organe>
			<qualiteDeclarant/>
			<qualiteDeclarantForPDF>D&#xe9;put&#xe9;/Seine-Saint-Denis(93)</qualiteDeclarantForPDF>
			<dateDebutMandat>08/07/2024</dateDebutMandat>
			<dateFinMandat/>
			<dateDernDeclar/>
			<regimeMatrimonial/>
			<regimeMatrimonialComments/>
			<nomSociete/>
			<nomSocieteMere/>
			<chiffreAffaire/>
			<nbLogements/>
			<declarationModificative>false</declarationModificative>
			<etablissement/>
			<declarant>
				<civilite>Mme</civilite>
				<nom>Trouv&#xe9;</nom>
				<prenom>Aur&#xe9;lie</prenom>
				<email>
            [Donn&#xe9;es non publi&#xe9;es]
        </email>
				<dateNaissance>20/09/1979</dateNaissance>
				<pieceIdentite/>
				<telephoneDec>
            [Donn&#xe9;es non publi&#xe9;es]
        </telephoneDec>
				<adresseDec>
					<voie>
            [Donn&#xe9;es non publi&#xe9;es]
        </voie>
					<complement>
            [Donn&#xe9;es non publi&#xe9;es]
        </complement>
					<codePostal>
            [Donn&#xe9;es non publi&#xe9;es]
        </codePostal>
					<ville>
            [Donn&#xe9;es non publi&#xe9;es]
        </ville>
					<pays>
            [Donn&#xe9;es non publi&#xe9;es]
        </pays>
				</adresseDec>
			</declarant>
		</general>
	</declaration>
<declaration>
		<dateDepot>12/10/2024 11:28:54</dateDepot>
		<uuid>861435e6-0a98-4c7e-8716-fcd746b0593d</uuid>
		<origine>ADEL</origine>
		<complete>true</complete>
		<attachedFiles>
			<attachedFiles>
				<fileName>VUE_PDF_DU_RECEPISSE_DU_DEPOT_XML</fileName>
				<serverFileName/>
				<base64EncodedContent/>
			</attachedFiles>
		</attachedFiles>
		<declarationVersion>20171221</declarationVersion>
		<activConsultantDto>
			<neant>true</neant>
		</activConsultantDto>
		<activProfCinqDerniereDto>
			<items>
				<items>
					<motif>
						<id>CREATION</id>
						<label/>
					</motif>
					<commentaire/>
					<description>enseignante chercheuse</description>
					<employeur>Minist&#xe8;re de l&apos;agriculture</employeur>
					<remuneration>
						<brutNet>Net</brutNet>
						<montant>
							<montant>
								<annee>2017</annee>
								<montant>39 300</montant>
							</montant>
							<montant>
								<annee>2018</annee>
								<montant>39 300</montant>
							</montant>
							<montant>
								<annee>2019</annee>
								<montant>45 200</montant>
							</montant>
							<montant>
								<annee>2020</annee>
								<montant>39 200</montant>
							</montant>
							<montant>
								<annee>2021</annee>
								<montant>43 500</montant>
							</montant>
							<montant>
								<annee>2022</annee>
								<montant>27 600</montant>
							</montant>
						</montant>
					</remuneration>
					<dateDebut>01/2017</dateDebut>
					<dateFin>06/2022</dateFin>
				</items>
			</items>
			<neant>false</neant>
		</activProfCinqDerniereDto>
		<activProfConjointDto>
			<items>
				<items>
					<motif>
						<id>CREATION</id>
						<label/>
					</motif>
					<commentaire/>
					<nomConjoint>
            [Donn&#xe9;es non publi&#xe9;es]
        </nomConjoint>
					<employeurConjoint>EELV</employeurConjoint>
					<activiteProf>charg&#xe9; de mission</activiteProf>
				</items>
			</items>
			<neant>false</neant>
		</activProfConjointDto>
		<fonctionBenevoleDto>
			<items>
				<items>
					<motif>
						<id>CREATION</id>
						<label/>
					</motif>
					<commentaire/>
					<conservee>true</conservee>
					<nomStructure>Membre de l&apos;acad&#xe9;mie d&apos;agriculture</nomStructure>
					<descriptionActivite>Simple membre avec participation occasionnelle &#xe0; des discussions et travaux (mise en suspend depuis le d&#xe9;but du mandat de d&#xe9;put&#xe9;e)</descriptionActivite>
				</items>
			</items>
			<neant>false</neant>
		</fonctionBenevoleDto>
		<mandatElectifDto>
			<items>
				<items>
					<motif>
						<id>CREATION</id>
						<label/>
					</motif>
					<commentaire/>
					<conservee>true</conservee>
					<descriptionMandat>d&#xe9;put&#xe9;e</descriptionMandat>
					<remuneration>
						<brutNet>Net</brutNet>
						<montant>
							<montant>
								<annee>2022</annee>
								<montant>39 016</montant>
							</montant>
							<montant>
								<annee>2023</annee>
								<montant>75 489</montant>
							</montant>
							<montant>
								<annee>2024</annee>
								<montant>37 872</montant>
							</montant>
						</montant>
					</remuneration>
					<dateDebut>06/2022</dateDebut>
					<dateFin>06/2024</dateFin>
				</items>
			</items>
			<neant>false</neant>
		</mandatElectifDto>
		<participationDirigeantDto>
			<items>
				<items>
					<motif>
						<id>CREATION</id>
						<label/>
					</motif>
					<commentaire/>
					<nomSociete>Attac</nomSociete>
					<activite>pr&#xe9;sidente</activite>
					<remuneration>
						<brutNet>Net</brutNet>
						<montant>
							<montant>
								<annee>2017</annee>
								<montant>0</montant>
							</montant>
							<montant>
								<annee>2018</annee>
								<montant>0</montant>
							</montant>
							<montant>
								<annee>2019</annee>
								<montant>0</montant>
							</montant>
							<montant>
								<annee>2020</annee>
								<montant>0</montant>
							</montant>
							<montant>
								<annee>2021</annee>
								<montant>0</montant>
							</montant>
						</montant>
					</remuneration>
					<dateDebut>06/2017</dateDebut>
					<dateFin>10/2021</dateFin>
				</items>
				<items>
					<motif>
						<id>CREATION</id>
						<label/>
					</motif>
					<commentaire/>
					<nomSociete>AgroParisTech</nomSociete>
					<activite>membre du conseil d&apos;administration</activite>
					<remuneration>
						<brutNet>Net</brutNet>
						<montant>
							<montant>
								<annee>2018</annee>
								<montant>0</montant>
							</montant>
							<montant>
								<annee>2019</annee>
								<montant>0</montant>
							</montant>
							<montant>
								<annee>2020</annee>
								<montant>0</montant>
							</montant>
							<montant>
								<annee>2021</annee>
								<montant>0</montant>
							</montant>
						</montant>
					</remuneration>
					<dateDebut>06/2018</dateDebut>
					<dateFin>06/2021</dateFin>
				</items>
				<items>
					<motif>
						<id>CREATION</id>
						<label/>
					</motif>
					<commentaire/>
					<conservee>true</conservee>
					<nomSociete>fonds de dotation de l&apos;Institut la Bo&#xe9;tie</nomSociete>
					<activite>membre du Conseil d&apos;administration</activite>
					<remuneration>
						<brutNet>Net</brutNet>
						<montant>
							<montant>
								<annee>2023</annee>
								<montant>0</montant>
							</montant>
						</montant>
					</remuneration>
					<dateDebut>06/2023</dateDebut>
					<dateFin/>
				</items>
			</items>
			<neant>false</neant>
		</participationDirigeantDto>
		<participationFinanciereDto>
			<neant>true</neant>
		</participationFinanciereDto>
		<activCollaborateursDto>
			<items>
				<items>
					<motif>
						<id>CREATION</id>
						<label/>
					</motif>
					<commentaire/>
					<nom>Am&#xe9;lie Canonne</nom>
					<employeur/>
					<descriptionActivite>collaborateur parlementaire</descriptionActivite>
				</items>
				<items>
					<motif>
						<id>CREATION</id>
						<label/>
					</motif>
					<commentaire/>
					<nom>Juliette Vellat</nom>
					<employeur/>
					<descriptionActivite>Collaborateur parlementaire</descriptionActivite>
				</items>
				<items>
					<motif>
						<id>CREATION</id>
						<label/>
					</motif>
					<commentaire/>
					<nom>Fadigua Aminata</nom>
					<employeur/>
					<descriptionActivite>collaboratrice parlementaire</descriptionActivite>
				</items>
			</items>
			<neant>false</neant>
		</activCollaborateursDto>
		<observationInteretDto>
			<neant>true</neant>
		</observationInteretDto>
		<general>
			<typeDeclaration>
				<id>DIA</id>
				<label>D&#xe9;claration d&apos;int&#xe9;r&#xea;ts et d&apos;activit&#xe9;s modificative</label>
			</typeDeclaration>
			<mandat>
				<label>D&#xe9;put&#xe9; ou s&#xe9;nateur</label>
			</mandat>
			<qualiteMandat>
				<typeMandat>D&#xe9;put&#xe9;</typeMandat>
				<codCategorieMandat>PAR</codCategorieMandat>
				<nomCategorieMandat>D&#xe9;put&#xe9; ou s&#xe9;nateur</nomCategorieMandat>
				<codTypeMandatFichier>depute</codTypeMandatFichier>
				<labelTypeMandat>D&#xe9;put&#xe9;</labelTypeMandat>
				<labelOrgane>D&#xe9;partement d&apos;&#xe9;lection</labelOrgane>
				<codeListeOrgane>ZEP</codeListeOrgane>
			</qualiteMandat>
			<organe>
				<codeOrgane>93</codeOrgane>
				<codeListeOrgane>ZEP</codeListeOrgane>
				<nomListeOrgane>Zones d&apos;&#xe9;lection des parlementaires</nomListeOrgane>
				<labelOrgane>Seine-Saint-Denis(93)</labelOrgane>
				<labelDeclaration/>
				<organeParent/>
				<horsLoi3DS>false</horsLoi3DS>
			</organe>
			<qualiteDeclarant/>
			<qualiteDeclarantForPDF>D&#xe9;put&#xe9;/Seine-Saint-Denis(93)</qualiteDeclarantForPDF>
			<dateDebutMandat>07/07/2024</dateDebutMandat>
			<dateFinMandat/>
			<dateDernDeclar/>
			<regimeMatrimonial/>
			<regimeMatrimonialComments/>
			<nomSociete/>
			<nomSocieteMere/>
			<chiffreAffaire/>
			<nbLogements/>
			<declarationModificative>true</declarationModificative>
			<etablissement/>
			<declarant>
				<civilite>Mme</civilite>
				<nom>Trouv&#xe9;</nom>
				<prenom>Aur&#xe9;lie</prenom>
				<email>
            [Donn&#xe9;es non publi&#xe9;es]
        </email>
				<dateNaissance>20/09/1979</dateNaissance>
				<pieceIdentite/>
				<telephoneDec>
            [Donn&#xe9;es non publi&#xe9;es]
        </telephoneDec>
				<adresseDec>
					<voie>
            [Donn&#xe9;es non publi&#xe9;es]
        </voie>
					<complement>
            [Donn&#xe9;es non publi&#xe9;es]
        </complement>
					<codePostal>
            [Donn&#xe9;es non publi&#xe9;es]
        </codePostal>
					<ville>
            [Donn&#xe9;es non publi&#xe9;es]
        </ville>
					<pays>
            [Donn&#xe9;es non publi&#xe9;es]
        </pays>
				</adresseDec>
			</declarant>
		</general>
	</declaration>