<declaration>
		<dateDepot>28/07/2024 20:04:36</dateDepot>
		<uuid>c476c8c2-1dbf-4cca-a3d0-02d3f7ac55ee</uuid>
		<origine>ADEL</origine>
		<complete>true</complete>
		<attachedFiles>
			<attachedFiles>
				<fileName>VUE_PDF_DU_RECEPISSE_DU_DEPOT_XML</fileName>
				<serverFileName/>
				<base64EncodedContent/>
			</attachedFiles>
		</attachedFiles>
		<declarationVersion>20171221</declarationVersion>
		<activConsultantDto>
			<items>
				<items>
					<motif>
						<id>CREATION</id>
						<label/>
					</motif>
					<commentaire>Auto-entreprise cr&#xe9;&#xe9;e fin novembre 2021 dans un but de conseil en communication. Mais 0&#x20ac; de chiffre d&apos;affaires depuis sa cr&#xe9;ation puisqu&apos;elle n&apos;a jamais &#xe9;t&#xe9; utilis&#xe9;e et n&apos;a pas vocation &#xe0; &#xea;tre utilis&#xe9;e durant l&apos;int&#xe9;gralit&#xe9; du mandat de d&#xe9;put&#xe9;. Cessation d&apos;activit&#xe9; le 04/11/2022.</commentaire>
					<conservee>false</conservee>
					<nomEmployeur>Alexandre Loubet (autoentreprise)</nomEmployeur>
					<description>Autoentreprise pour conseil en communication</description>
					<dateDebut>11/2021</dateDebut>
					<dateFin>11/2022</dateFin>
					<remuneration>
						<brutNet>Net</brutNet>
						<montant>
							<montant>
								<annee>2021</annee>
								<montant>0</montant>
							</montant>
							<montant>
								<annee>2022</annee>
								<montant>0</montant>
							</montant>
						</montant>
					</remuneration>
				</items>
			</items>
			<neant>false</neant>
		</activConsultantDto>
		<activProfCinqDerniereDto>
			<items>
				<items>
					<motif>
						<id>CREATION</id>
						<label/>
					</motif>
					<commentaire/>
					<description>Responsable de la communication de la campagne l&#xe9;gislative</description>
					<employeur>Rassemblement National</employeur>
					<remuneration>
						<brutNet>Net</brutNet>
						<montant>
							<montant>
								<annee>2022</annee>
								<montant>11 364</montant>
							</montant>
						</montant>
					</remuneration>
					<dateDebut>04/2022</dateDebut>
					<dateFin>06/2022</dateFin>
				</items>
				<items>
					<motif>
						<id>CREATION</id>
						<label/>
					</motif>
					<commentaire>Campagne pr&#xe9;sidentielle de Marine Le Pen</commentaire>
					<description>Relations presse et directeur de la communication de la campagne</description>
					<employeur>AFE MLP 2022</employeur>
					<remuneration>
						<brutNet>Net</brutNet>
						<montant>
							<montant>
								<annee>2021</annee>
								<montant>16 587</montant>
							</montant>
							<montant>
								<annee>2022</annee>
								<montant>24 853</montant>
							</montant>
						</montant>
					</remuneration>
					<dateDebut>09/2021</dateDebut>
					<dateFin>04/2022</dateFin>
				</items>
				<items>
					<motif>
						<id>CREATION</id>
						<label/>
					</motif>
					<commentaire>Cong&#xe9; sans solde de septembre 2021 &#xe0; juin 2022 puis rupture de contrat en juin 2022.</commentaire>
					<description>Collaborateur parlementaire</description>
					<employeur>Nicolas Meizonnet - D&#xe9;put&#xe9; employeur</employeur>
					<remuneration>
						<brutNet>Net</brutNet>
						<montant>
							<montant>
								<annee>2021</annee>
								<montant>27 468</montant>
							</montant>
							<montant>
								<annee>2022</annee>
								<montant>1 131</montant>
							</montant>
						</montant>
					</remuneration>
					<dateDebut>01/2021</dateDebut>
					<dateFin>06/2022</dateFin>
				</items>
				<items>
					<motif>
						<id>CREATION</id>
						<label/>
					</motif>
					<commentaire/>
					<description>Collaborateur parlementaire</description>
					<employeur>Nicolas Dupont-Aignan - D&#xe9;put&#xe9; employeur</employeur>
					<remuneration>
						<brutNet>Net</brutNet>
						<montant>
							<montant>
								<annee>2019</annee>
								<montant>17 251</montant>
							</montant>
							<montant>
								<annee>2020</annee>
								<montant>17 186</montant>
							</montant>
						</montant>
					</remuneration>
					<dateDebut>06/2019</dateDebut>
					<dateFin>12/2020</dateFin>
				</items>
				<items>
					<motif>
						<id>CREATION</id>
						<label/>
					</motif>
					<commentaire/>
					<description>Directeur de la communication</description>
					<employeur>Debout La France</employeur>
					<remuneration>
						<brutNet>Net</brutNet>
						<montant>
							<montant>
								<annee>2018</annee>
								<montant>14 620</montant>
							</montant>
							<montant>
								<annee>2019</annee>
								<montant>27 093</montant>
							</montant>
							<montant>
								<annee>2020</annee>
								<montant>22 649</montant>
							</montant>
						</montant>
					</remuneration>
					<dateDebut>09/2018</dateDebut>
					<dateFin>12/2020</dateFin>
				</items>
				<items>
					<motif>
						<id>CREATION</id>
						<label/>
					</motif>
					<commentaire>Stage de fin d&apos;&#xe9;tudes &#xe0; EDF.</commentaire>
					<description>Charg&#xe9; de mission (stagiaire)</description>
					<employeur>Electricit&#xe9; de France (EDF)</employeur>
					<remuneration>
						<brutNet>Net</brutNet>
						<montant>
							<montant>
								<annee>2018</annee>
								<montant>5 770</montant>
							</montant>
						</montant>
					</remuneration>
					<dateDebut>01/2018</dateDebut>
					<dateFin>06/2018</dateFin>
				</items>
			</items>
			<neant>false</neant>
		</activProfCinqDerniereDto>
		<activProfConjointDto>
			<items/>
			<neant>true</neant>
		</activProfConjointDto>
		<fonctionBenevoleDto>
			<items/>
			<neant>true</neant>
		</fonctionBenevoleDto>
		<mandatElectifDto>
			<items>
				<items>
					<motif>
						<id>CREATION</id>
						<label/>
					</motif>
					<commentaire/>
					<conservee>false</conservee>
					<descriptionMandat>D&#xe9;put&#xe9; de la Moselle - L&#xe9;gislature XVI</descriptionMandat>
					<remuneration>
						<brutNet>Net</brutNet>
						<montant>
							<montant>
								<annee>2022</annee>
								<montant>37 207</montant>
							</montant>
							<montant>
								<annee>2023</annee>
								<montant>73 698</montant>
							</montant>
							<montant>
								<annee>2024</annee>
								<montant>37 278</montant>
							</montant>
						</montant>
					</remuneration>
					<dateDebut>06/2022</dateDebut>
					<dateFin>06/2024</dateFin>
				</items>
			</items>
			<neant>false</neant>
		</mandatElectifDto>
		<participationDirigeantDto>
			<items>
				<items>
					<motif>
						<id>CREATION</id>
						<label/>
					</motif>
					<commentaire>Salaire relatif &#xe0; la fonction pr&#xe9;cis&#xe9; dans l&apos;onglet &quot;activit&#xe9;s professionnelles&quot;</commentaire>
					<nomSociete>Debout La France</nomSociete>
					<activite>Directeur de la communication</activite>
					<remuneration>
						<brutNet>Net</brutNet>
						<montant>
							<montant>
								<annee>2018</annee>
								<montant>0</montant>
							</montant>
							<montant>
								<annee>2019</annee>
								<montant>0</montant>
							</montant>
							<montant>
								<annee>2020</annee>
								<montant>0</montant>
							</montant>
						</montant>
					</remuneration>
					<dateDebut>09/2018</dateDebut>
					<dateFin>11/2020</dateFin>
				</items>
				<items>
					<motif>
						<id>CREATION</id>
						<label/>
					</motif>
					<commentaire>Secr&#xe9;taire g&#xe9;n&#xe9;ral de L&apos;Avenir Fran&#xe7;ais associaton de loi 1901 &#xe0; caract&#xe8;re politique. Engagement b&#xe9;n&#xe9;vole.</commentaire>
					<conservee>true</conservee>
					<nomSociete>L&apos;Avenir Fran&#xe7;ais !</nomSociete>
					<activite>Secr&#xe9;taire g&#xe9;n&#xe9;ral</activite>
					<remuneration>
						<brutNet>Net</brutNet>
						<montant>
							<montant>
								<annee>2021</annee>
								<montant>0</montant>
							</montant>
							<montant>
								<annee>2022</annee>
								<montant>0</montant>
							</montant>
						</montant>
					</remuneration>
					<dateDebut>02/2021</dateDebut>
					<dateFin/>
				</items>
				<items>
					<motif>
						<id>CREATION</id>
						<label/>
					</motif>
					<commentaire>D&apos;ao&#xfb;t 2015 &#xe0; mai 2018 pr&#xe9;sident des Jeunes de Debout La France. Engagement b&#xe9;n&#xe9;vole.</commentaire>
					<nomSociete>Debout La France</nomSociete>
					<activite>Pr&#xe9;sident des jeunes</activite>
					<remuneration>
						<brutNet>Net</brutNet>
						<montant>
							<montant>
								<annee>2016</annee>
								<montant>0</montant>
							</montant>
							<montant>
								<annee>2017</annee>
								<montant>0</montant>
							</montant>
							<montant>
								<annee>2018</annee>
								<montant>0</montant>
							</montant>
						</montant>
					</remuneration>
					<dateDebut>01/2016</dateDebut>
					<dateFin>05/2018</dateFin>
				</items>
				<items>
					<motif>
						<id>CREATION</id>
						<label/>
					</motif>
					<commentaire>Engagement b&#xe9;n&#xe9;vole. Membre du comit&#xe9; de direction du RN en qualit&#xe9; de responsable de la communication. La fonction devrait prendre fin au plus tard au congr&#xe8;s du RN de novembre 2022.</commentaire>
					<nomSociete>Rassemblement National</nomSociete>
					<activite>Directeur de la communication</activite>
					<remuneration>
						<brutNet>Net</brutNet>
						<montant>
							<montant>
								<annee>2021</annee>
								<montant>0</montant>
							</montant>
							<montant>
								<annee>2022</annee>
								<montant>0</montant>
							</montant>
						</montant>
					</remuneration>
					<dateDebut>09/2021</dateDebut>
					<dateFin>11/2022</dateFin>
				</items>
				<items>
					<motif>
						<id>CREATION</id>
						<label/>
					</motif>
					<commentaire>Membre du Conseil National du RN depuis le Congr&#xe8;s du 5 novembre 2022.</commentaire>
					<conservee>true</conservee>
					<nomSociete>Rassemblement National</nomSociete>
					<activite>Membre du Conseil National</activite>
					<remuneration>
						<brutNet>Net</brutNet>
						<montant>
							<montant>
								<annee>2022</annee>
								<montant>0</montant>
							</montant>
						</montant>
					</remuneration>
					<dateDebut>11/2022</dateDebut>
					<dateFin/>
				</items>
				<items>
					<motif>
						<id>CREATION</id>
						<label/>
					</motif>
					<commentaire>Membre du Bureau National du RN depuis le Congr&#xe8;s du 5 novembre 2022.</commentaire>
					<conservee>true</conservee>
					<nomSociete>Rassemblement National</nomSociete>
					<activite>Membre du Bureau National</activite>
					<remuneration>
						<brutNet>Net</brutNet>
						<montant>
							<montant>
								<annee>2022</annee>
								<montant>0</montant>
							</montant>
						</montant>
					</remuneration>
					<dateDebut>11/2022</dateDebut>
					<dateFin/>
				</items>
				<items>
					<motif>
						<id>CREATION</id>
						<label/>
					</motif>
					<commentaire>Fonction b&#xe9;n&#xe9;vole qui a pris fin au lendemain des &#xe9;lections europ&#xe9;ennes du 9 juin 2024.</commentaire>
					<conservee>false</conservee>
					<nomSociete>Rassemblement National / AFE Jordan Bardella - Europ&#xe9;ennes 2024</nomSociete>
					<activite>Directeur de campagne du RN pour les &#xe9;lections europ&#xe9;ennes 2024</activite>
					<remuneration>
						<brutNet>Net</brutNet>
						<montant>
							<montant>
								<annee>2023</annee>
								<montant>0</montant>
							</montant>
							<montant>
								<annee>2024</annee>
								<montant>0</montant>
							</montant>
						</montant>
					</remuneration>
					<dateDebut>05/2023</dateDebut>
					<dateFin>06/2024</dateFin>
				</items>
				<items>
					<motif>
						<id>CREATION</id>
						<label/>
					</motif>
					<commentaire>Fonction b&#xe9;n&#xe9;vole du 10 juin au 7 juillet 2024.</commentaire>
					<conservee>false</conservee>
					<nomSociete>Rassemblement National</nomSociete>
					<activite>Directeur de campagne du RN pour les &#xe9;lections l&#xe9;gislatives anticip&#xe9;es 2024</activite>
					<remuneration>
						<brutNet>Net</brutNet>
						<montant>
							<montant>
								<annee>2024</annee>
								<montant>0</montant>
							</montant>
						</montant>
					</remuneration>
					<dateDebut>06/2024</dateDebut>
					<dateFin>07/2024</dateFin>
				</items>
				<items>
					<motif>
						<id>CREATION</id>
						<label/>
					</motif>
					<commentaire>Fonction b&#xe9;n&#xe9;vole.</commentaire>
					<conservee>true</conservee>
					<nomSociete>Groupe RN &#xe0; l&apos;Assembl&#xe9;e nationale</nomSociete>
					<activite>Vice-pr&#xe9;sident</activite>
					<remuneration>
						<brutNet>Net</brutNet>
						<montant>
							<montant>
								<annee>2022</annee>
								<montant>0</montant>
							</montant>
							<montant>
								<annee>2023</annee>
								<montant>0</montant>
							</montant>
							<montant>
								<annee>2024</annee>
								<montant>0</montant>
							</montant>
						</montant>
					</remuneration>
					<dateDebut>07/2022</dateDebut>
					<dateFin/>
				</items>
			</items>
			<neant>false</neant>
		</participationDirigeantDto>
		<participationFinanciereDto>
			<items>
				<items>
					<motif>
						<id>CREATION</id>
						<label/>
					</motif>
					<commentaire>
        [Donn&#xe9;es non publi&#xe9;es]
    </commentaire>
					<nomSociete>SCI 
        [Donn&#xe9;es non publi&#xe9;es]
    </nomSociete>
					<evaluation>29670</evaluation>
					<remuneration>49&#x20ac; de revenus fonciers en 2023 concernant les revenus locatifs.</remuneration>
					<capitalDetenu>45</capitalDetenu>
					<nombreParts>45</nombreParts>
					<actiConseil>Non</actiConseil>
				</items>
			</items>
			<neant>false</neant>
		</participationFinanciereDto>
		<activCollaborateursDto>
			<items>
				<items>
					<motif>
						<id>CREATION</id>
						<label/>
					</motif>
					<commentaire>N&#xe9;ant</commentaire>
					<nom>CHATELAIN Magali</nom>
					<employeur>N&#xe9;ant</employeur>
					<descriptionActivite>N&#xe9;ant</descriptionActivite>
				</items>
				<items>
					<motif>
						<id>CREATION</id>
						<label/>
					</motif>
					<commentaire>N&#xe9;ant</commentaire>
					<nom>HEILIG Angelo</nom>
					<employeur>N&#xe9;ant</employeur>
					<descriptionActivite>N&#xe9;ant</descriptionActivite>
				</items>
				<items>
					<motif>
						<id>CREATION</id>
						<label/>
					</motif>
					<commentaire>N&#xe9;ant</commentaire>
					<nom>BERTHONNEAU R&#xe9;my</nom>
					<employeur>Autoentreprise RB R&#xe9;my Berthonneau</employeur>
					<descriptionActivite>Conseil en strat&#xe9;gie aucune mission en cours.</descriptionActivite>
				</items>
			</items>
			<neant>false</neant>
		</activCollaborateursDto>
		<observationInteretDto>
			<items/>
			<neant>true</neant>
		</observationInteretDto>
		<general>
			<typeDeclaration>
				<id>DIA</id>
				<label>D&#xe9;claration d&apos;int&#xe9;r&#xea;ts et d&apos;activit&#xe9;s</label>
			</typeDeclaration>
			<mandat>
				<label>D&#xe9;put&#xe9; ou s&#xe9;nateur</label>
			</mandat>
			<qualiteMandat>
				<typeMandat>D&#xe9;put&#xe9;</typeMandat>
				<codCategorieMandat>PAR</codCategorieMandat>
				<nomCategorieMandat>D&#xe9;put&#xe9; ou s&#xe9;nateur</nomCategorieMandat>
				<codTypeMandatFichier>depute</codTypeMandatFichier>
				<labelTypeMandat>D&#xe9;put&#xe9;</labelTypeMandat>
				<labelOrgane>D&#xe9;partement d&apos;&#xe9;lection</labelOrgane>
				<codeListeOrgane>ZEP</codeListeOrgane>
			</qualiteMandat>
			<organe>
				<codeOrgane>57</codeOrgane>
				<codeListeOrgane>ZEP</codeListeOrgane>
				<nomListeOrgane>Zones d&apos;&#xe9;lection des parlementaires</nomListeOrgane>
				<labelOrgane>Moselle(57)</labelOrgane>
				<labelDeclaration/>
				<organeParent/>
				<horsLoi3DS>false</horsLoi3DS>
			</organe>
			<qualiteDeclarant/>
			<qualiteDeclarantForPDF>D&#xe9;put&#xe9;/Moselle(57)</qualiteDeclarantForPDF>
			<dateDebutMandat>30/06/2030</dateDebutMandat>
			<dateFinMandat/>
			<dateDernDeclar/>
			<regimeMatrimonial/>
			<regimeMatrimonialComments/>
			<nomSociete/>
			<nomSocieteMere/>
			<chiffreAffaire/>
			<nbLogements/>
			<declarationModificative>false</declarationModificative>
			<etablissement/>
			<declarant>
				<civilite>M.</civilite>
				<nom>LOUBET</nom>
				<prenom>Alexandre</prenom>
				<email>
            [Donn&#xe9;es non publi&#xe9;es]
        </email>
				<dateNaissance>07/07/1994</dateNaissance>
				<pieceIdentite/>
				<telephoneDec>
            [Donn&#xe9;es non publi&#xe9;es]
        </telephoneDec>
				<adresseDec>
					<voie>
            [Donn&#xe9;es non publi&#xe9;es]
        </voie>
					<complement>
            [Donn&#xe9;es non publi&#xe9;es]
        </complement>
					<codePostal>
            [Donn&#xe9;es non publi&#xe9;es]
        </codePostal>
					<ville>
            [Donn&#xe9;es non publi&#xe9;es]
        </ville>
					<pays>
            [Donn&#xe9;es non publi&#xe9;es]
        </pays>
				</adresseDec>
			</declarant>
		</general>
	</declaration>
<declaration>
		<dateDepot>14/11/2024 17:53:52</dateDepot>
		<uuid>e1f6b991-18a5-47cc-b483-53fc3cf93ccc</uuid>
		<origine>ADEL</origine>
		<complete>true</complete>
		<attachedFiles>
			<attachedFiles>
				<fileName>VUE_PDF_DU_RECEPISSE_DU_DEPOT_XML</fileName>
				<serverFileName/>
				<base64EncodedContent/>
			</attachedFiles>
		</attachedFiles>
		<declarationVersion>20171221</declarationVersion>
		<activConsultantDto>
			<items>
				<items>
					<motif>
						<id>CREATION</id>
						<label/>
					</motif>
					<commentaire>Auto-entreprise cr&#xe9;&#xe9;e fin novembre 2021 dans un but de conseil en communication. Mais 0&#x20ac; de chiffre d&apos;affaires depuis sa cr&#xe9;ation puisqu&apos;elle n&apos;a jamais &#xe9;t&#xe9; utilis&#xe9;e et n&apos;a pas vocation &#xe0; &#xea;tre utilis&#xe9;e durant l&apos;int&#xe9;gralit&#xe9; du mandat de d&#xe9;put&#xe9;. Cessation d&apos;activit&#xe9; le 04/11/2022.</commentaire>
					<conservee>false</conservee>
					<nomEmployeur>Alexandre Loubet (autoentreprise)</nomEmployeur>
					<description>Autoentreprise pour conseil en communication</description>
					<dateDebut>11/2021</dateDebut>
					<dateFin>11/2022</dateFin>
					<remuneration>
						<brutNet>Net</brutNet>
						<montant>
							<montant>
								<annee>2021</annee>
								<montant>0</montant>
							</montant>
							<montant>
								<annee>2022</annee>
								<montant>0</montant>
							</montant>
						</montant>
					</remuneration>
				</items>
			</items>
			<neant>false</neant>
		</activConsultantDto>
		<activProfCinqDerniereDto>
			<items>
				<items>
					<motif>
						<id>CREATION</id>
						<label/>
					</motif>
					<commentaire/>
					<description>Responsable de la communication de la campagne l&#xe9;gislative</description>
					<employeur>Rassemblement National</employeur>
					<remuneration>
						<brutNet>Net</brutNet>
						<montant>
							<montant>
								<annee>2022</annee>
								<montant>11 364</montant>
							</montant>
						</montant>
					</remuneration>
					<dateDebut>04/2022</dateDebut>
					<dateFin>06/2022</dateFin>
				</items>
				<items>
					<motif>
						<id>CREATION</id>
						<label/>
					</motif>
					<commentaire>Campagne pr&#xe9;sidentielle de Marine Le Pen</commentaire>
					<description>Relations presse et directeur de la communication de la campagne</description>
					<employeur>AFE MLP 2022</employeur>
					<remuneration>
						<brutNet>Net</brutNet>
						<montant>
							<montant>
								<annee>2021</annee>
								<montant>16 587</montant>
							</montant>
							<montant>
								<annee>2022</annee>
								<montant>24 853</montant>
							</montant>
						</montant>
					</remuneration>
					<dateDebut>09/2021</dateDebut>
					<dateFin>04/2022</dateFin>
				</items>
				<items>
					<motif>
						<id>CREATION</id>
						<label/>
					</motif>
					<commentaire>Cong&#xe9; sans solde de septembre 2021 &#xe0; juin 2022 puis rupture de contrat en juin 2022.</commentaire>
					<description>Collaborateur parlementaire</description>
					<employeur>Nicolas Meizonnet - D&#xe9;put&#xe9; employeur</employeur>
					<remuneration>
						<brutNet>Net</brutNet>
						<montant>
							<montant>
								<annee>2021</annee>
								<montant>27 468</montant>
							</montant>
							<montant>
								<annee>2022</annee>
								<montant>1 131</montant>
							</montant>
						</montant>
					</remuneration>
					<dateDebut>01/2021</dateDebut>
					<dateFin>06/2022</dateFin>
				</items>
				<items>
					<motif>
						<id>CREATION</id>
						<label/>
					</motif>
					<commentaire/>
					<description>Collaborateur parlementaire</description>
					<employeur>Nicolas Dupont-Aignan - D&#xe9;put&#xe9; employeur</employeur>
					<remuneration>
						<brutNet>Net</brutNet>
						<montant>
							<montant>
								<annee>2019</annee>
								<montant>17 251</montant>
							</montant>
							<montant>
								<annee>2020</annee>
								<montant>17 186</montant>
							</montant>
						</montant>
					</remuneration>
					<dateDebut>06/2019</dateDebut>
					<dateFin>12/2020</dateFin>
				</items>
				<items>
					<motif>
						<id>CREATION</id>
						<label/>
					</motif>
					<commentaire/>
					<description>Directeur de la communication</description>
					<employeur>Debout La France</employeur>
					<remuneration>
						<brutNet>Net</brutNet>
						<montant>
							<montant>
								<annee>2018</annee>
								<montant>14 620</montant>
							</montant>
							<montant>
								<annee>2019</annee>
								<montant>27 093</montant>
							</montant>
							<montant>
								<annee>2020</annee>
								<montant>22 649</montant>
							</montant>
						</montant>
					</remuneration>
					<dateDebut>09/2018</dateDebut>
					<dateFin>12/2020</dateFin>
				</items>
			</items>
			<neant>false</neant>
		</activProfCinqDerniereDto>
		<activProfConjointDto>
			<items/>
			<neant>true</neant>
		</activProfConjointDto>
		<fonctionBenevoleDto>
			<items/>
			<neant>true</neant>
		</fonctionBenevoleDto>
		<mandatElectifDto>
			<items>
				<items>
					<motif>
						<id>CREATION</id>
						<label/>
					</motif>
					<commentaire/>
					<conservee>false</conservee>
					<descriptionMandat>D&#xe9;put&#xe9; de la Moselle - L&#xe9;gislature XVI</descriptionMandat>
					<remuneration>
						<brutNet>Net</brutNet>
						<montant>
							<montant>
								<annee>2022</annee>
								<montant>37 207</montant>
							</montant>
							<montant>
								<annee>2023</annee>
								<montant>73 698</montant>
							</montant>
							<montant>
								<annee>2024</annee>
								<montant>37 278</montant>
							</montant>
						</montant>
					</remuneration>
					<dateDebut>06/2022</dateDebut>
					<dateFin>06/2024</dateFin>
				</items>
			</items>
			<neant>false</neant>
		</mandatElectifDto>
		<participationDirigeantDto>
			<items>
				<items>
					<motif>
						<id>CREATION</id>
						<label/>
					</motif>
					<commentaire>Salaire relatif &#xe0; la fonction pr&#xe9;cis&#xe9; dans l&apos;onglet &quot;activit&#xe9;s professionnelles&quot;</commentaire>
					<nomSociete>Debout La France</nomSociete>
					<activite>Directeur de la communication</activite>
					<remuneration>
						<brutNet>Net</brutNet>
						<montant>
							<montant>
								<annee>2018</annee>
								<montant>0</montant>
							</montant>
							<montant>
								<annee>2019</annee>
								<montant>0</montant>
							</montant>
							<montant>
								<annee>2020</annee>
								<montant>0</montant>
							</montant>
						</montant>
					</remuneration>
					<dateDebut>09/2018</dateDebut>
					<dateFin>11/2020</dateFin>
				</items>
				<items>
					<motif>
						<id>CREATION</id>
						<label/>
					</motif>
					<commentaire>Secr&#xe9;taire g&#xe9;n&#xe9;ral de L&apos;Avenir Fran&#xe7;ais associaton de loi 1901 &#xe0; caract&#xe8;re politique. Engagement b&#xe9;n&#xe9;vole.</commentaire>
					<conservee>true</conservee>
					<nomSociete>L&apos;Avenir Fran&#xe7;ais !</nomSociete>
					<activite>Secr&#xe9;taire g&#xe9;n&#xe9;ral</activite>
					<remuneration>
						<brutNet>Net</brutNet>
						<montant>
							<montant>
								<annee>2021</annee>
								<montant>0</montant>
							</montant>
							<montant>
								<annee>2022</annee>
								<montant>0</montant>
							</montant>
						</montant>
					</remuneration>
					<dateDebut>02/2021</dateDebut>
					<dateFin/>
				</items>
				<items>
					<motif>
						<id>CREATION</id>
						<label/>
					</motif>
					<commentaire>Engagement b&#xe9;n&#xe9;vole. Membre du comit&#xe9; de direction du RN en qualit&#xe9; de responsable de la communication. La fonction devrait prendre fin au plus tard au congr&#xe8;s du RN de novembre 2022.</commentaire>
					<nomSociete>Rassemblement National</nomSociete>
					<activite>Directeur de la communication</activite>
					<remuneration>
						<brutNet>Net</brutNet>
						<montant>
							<montant>
								<annee>2021</annee>
								<montant>0</montant>
							</montant>
							<montant>
								<annee>2022</annee>
								<montant>0</montant>
							</montant>
						</montant>
					</remuneration>
					<dateDebut>09/2021</dateDebut>
					<dateFin>11/2022</dateFin>
				</items>
				<items>
					<motif>
						<id>CREATION</id>
						<label/>
					</motif>
					<commentaire>Membre du Conseil National du RN depuis le Congr&#xe8;s du 5 novembre 2022.</commentaire>
					<conservee>true</conservee>
					<nomSociete>Rassemblement National</nomSociete>
					<activite>Membre du Conseil National</activite>
					<remuneration>
						<brutNet>Net</brutNet>
						<montant>
							<montant>
								<annee>2022</annee>
								<montant>0</montant>
							</montant>
						</montant>
					</remuneration>
					<dateDebut>11/2022</dateDebut>
					<dateFin/>
				</items>
				<items>
					<motif>
						<id>CREATION</id>
						<label/>
					</motif>
					<commentaire>Membre du Bureau National du RN depuis le Congr&#xe8;s du 5 novembre 2022.</commentaire>
					<conservee>true</conservee>
					<nomSociete>Rassemblement National</nomSociete>
					<activite>Membre du Bureau National</activite>
					<remuneration>
						<brutNet>Net</brutNet>
						<montant>
							<montant>
								<annee>2022</annee>
								<montant>0</montant>
							</montant>
						</montant>
					</remuneration>
					<dateDebut>11/2022</dateDebut>
					<dateFin/>
				</items>
				<items>
					<motif>
						<id>CREATION</id>
						<label/>
					</motif>
					<commentaire>Fonction b&#xe9;n&#xe9;vole qui a pris fin au lendemain des &#xe9;lections europ&#xe9;ennes du 9 juin 2024.</commentaire>
					<conservee>false</conservee>
					<nomSociete>Rassemblement National / AFE Jordan Bardella - Europ&#xe9;ennes 2024</nomSociete>
					<activite>Directeur de campagne du RN pour les &#xe9;lections europ&#xe9;ennes 2024</activite>
					<remuneration>
						<brutNet>Net</brutNet>
						<montant>
							<montant>
								<annee>2023</annee>
								<montant>0</montant>
							</montant>
							<montant>
								<annee>2024</annee>
								<montant>0</montant>
							</montant>
						</montant>
					</remuneration>
					<dateDebut>05/2023</dateDebut>
					<dateFin>06/2024</dateFin>
				</items>
				<items>
					<motif>
						<id>CREATION</id>
						<label/>
					</motif>
					<commentaire>Fonction b&#xe9;n&#xe9;vole du 10 juin au 7 juillet 2024.</commentaire>
					<conservee>false</conservee>
					<nomSociete>Rassemblement National</nomSociete>
					<activite>Directeur de campagne du RN pour les &#xe9;lections l&#xe9;gislatives anticip&#xe9;es 2024</activite>
					<remuneration>
						<brutNet>Net</brutNet>
						<montant>
							<montant>
								<annee>2024</annee>
								<montant>0</montant>
							</montant>
						</montant>
					</remuneration>
					<dateDebut>06/2024</dateDebut>
					<dateFin>07/2024</dateFin>
				</items>
				<items>
					<motif>
						<id>CREATION</id>
						<label/>
					</motif>
					<commentaire>Fonction b&#xe9;n&#xe9;vole.</commentaire>
					<conservee>true</conservee>
					<nomSociete>Groupe RN &#xe0; l&apos;Assembl&#xe9;e nationale</nomSociete>
					<activite>Vice-pr&#xe9;sident</activite>
					<remuneration>
						<brutNet>Net</brutNet>
						<montant>
							<montant>
								<annee>2022</annee>
								<montant>0</montant>
							</montant>
							<montant>
								<annee>2023</annee>
								<montant>0</montant>
							</montant>
							<montant>
								<annee>2024</annee>
								<montant>0</montant>
							</montant>
						</montant>
					</remuneration>
					<dateDebut>07/2022</dateDebut>
					<dateFin/>
				</items>
				<items>
					<motif>
						<id>CREATION</id>
						<label/>
					</motif>
					<commentaire>49&#x20ac; de revenus fonciers en 2023 29&#x20ac; en 2022 55&#x20ac; en 2021 86&#x20ac; en 2020 et 24&#x20ac; en 2019 concernant les revenus locatifs. Revenu 2024 en attente il sera pr&#xe9;cis&#xe9; l&apos;an prochain (0 indiqu&#xe9; en attente).</commentaire>
					<conservee>true</conservee>
					<nomSociete>SCI 
        [Donn&#xe9;es non publi&#xe9;es]
    </nomSociete>
					<activite>Associ&#xe9; de la SCI</activite>
					<remuneration>
						<brutNet>Net</brutNet>
						<montant>
							<montant>
								<annee>2019</annee>
								<montant>24</montant>
							</montant>
							<montant>
								<annee>2020</annee>
								<montant>86</montant>
							</montant>
							<montant>
								<annee>2021</annee>
								<montant>55</montant>
							</montant>
							<montant>
								<annee>2022</annee>
								<montant>29</montant>
							</montant>
							<montant>
								<annee>2023</annee>
								<montant>49</montant>
							</montant>
							<montant>
								<annee>2024</annee>
								<montant>0</montant>
							</montant>
						</montant>
					</remuneration>
					<dateDebut>11/2019</dateDebut>
					<dateFin/>
				</items>
			</items>
			<neant>false</neant>
		</participationDirigeantDto>
		<participationFinanciereDto>
			<items>
				<items>
					<motif>
						<id>CREATION</id>
						<label/>
					</motif>
					<commentaire>
        [Donn&#xe9;es non publi&#xe9;es]
    </commentaire>
					<nomSociete>SCI 
        [Donn&#xe9;es non publi&#xe9;es]
    </nomSociete>
					<evaluation>15748</evaluation>
					<remuneration>49&#x20ac; de revenus fonciers en 2023 29&#x20ac; en 2022 55&#x20ac; en 2021 86&#x20ac; en 2020 et 24&#x20ac; en 2019 concernant les revenus locatifs.</remuneration>
					<capitalDetenu>45</capitalDetenu>
					<nombreParts>45</nombreParts>
					<actiConseil>Non</actiConseil>
				</items>
			</items>
			<neant>false</neant>
		</participationFinanciereDto>
		<activCollaborateursDto>
			<items>
				<items>
					<motif>
						<id>CREATION</id>
						<label/>
					</motif>
					<commentaire>N&#xe9;ant</commentaire>
					<nom>HEILIG Angelo</nom>
					<employeur>N&#xe9;ant</employeur>
					<descriptionActivite>N&#xe9;ant</descriptionActivite>
				</items>
				<items>
					<motif>
						<id>CREATION</id>
						<label/>
					</motif>
					<commentaire>N&#xe9;ant</commentaire>
					<nom>BERTHONNEAU R&#xe9;my</nom>
					<employeur>Autoentreprise RB R&#xe9;my Berthonneau</employeur>
					<descriptionActivite>Conseil en strat&#xe9;gie aucune mission en cours.</descriptionActivite>
				</items>
			</items>
			<neant>false</neant>
		</activCollaborateursDto>
		<observationInteretDto>
			<neant>true</neant>
		</observationInteretDto>
		<general>
			<typeDeclaration>
				<id>DIA</id>
				<label>D&#xe9;claration d&apos;int&#xe9;r&#xea;ts et d&apos;activit&#xe9;s modificative</label>
				<filtre/>
			</typeDeclaration>
			<mandat>
				<label>D&#xe9;put&#xe9; ou s&#xe9;nateur</label>
			</mandat>
			<qualiteMandat>
				<typeMandat>D&#xe9;put&#xe9;</typeMandat>
				<codCategorieMandat>PAR</codCategorieMandat>
				<nomCategorieMandat>D&#xe9;put&#xe9; ou s&#xe9;nateur</nomCategorieMandat>
				<codTypeMandatFichier>depute</codTypeMandatFichier>
				<labelTypeMandat>D&#xe9;put&#xe9;</labelTypeMandat>
				<labelOrgane>D&#xe9;partement d&apos;&#xe9;lection</labelOrgane>
				<codeListeOrgane>ZEP</codeListeOrgane>
			</qualiteMandat>
			<organe>
				<codeOrgane>57</codeOrgane>
				<codeListeOrgane>ZEP</codeListeOrgane>
				<nomListeOrgane>Zones d&apos;&#xe9;lection des parlementaires</nomListeOrgane>
				<labelOrgane>Moselle(57)</labelOrgane>
				<labelDeclaration/>
				<organeParent/>
				<horsLoi3DS>false</horsLoi3DS>
			</organe>
			<qualiteDeclarant/>
			<qualiteDeclarantForPDF>D&#xe9;put&#xe9;/Moselle(57)</qualiteDeclarantForPDF>
			<dateDebutMandat>30/06/2024</dateDebutMandat>
			<dateFinMandat/>
			<dateDernDeclar/>
			<regimeMatrimonial/>
			<regimeMatrimonialComments/>
			<nomSociete/>
			<nomSocieteMere/>
			<chiffreAffaire/>
			<nbLogements/>
			<declarationModificative>true</declarationModificative>
			<etablissement/>
			<declarant>
				<civilite>M.</civilite>
				<nom>LOUBET</nom>
				<prenom>Alexandre</prenom>
				<email>
            [Donn&#xe9;es non publi&#xe9;es]
        </email>
				<dateNaissance>07/07/1994</dateNaissance>
				<pieceIdentite/>
				<telephoneDec>
            [Donn&#xe9;es non publi&#xe9;es]
        </telephoneDec>
				<adresseDec>
					<voie>
            [Donn&#xe9;es non publi&#xe9;es]
        </voie>
					<complement>
            [Donn&#xe9;es non publi&#xe9;es]
        </complement>
					<codePostal>
            [Donn&#xe9;es non publi&#xe9;es]
        </codePostal>
					<ville>
            [Donn&#xe9;es non publi&#xe9;es]
        </ville>
					<pays>
            [Donn&#xe9;es non publi&#xe9;es]
        </pays>
				</adresseDec>
			</declarant>
		</general>
	</declaration>